Workbook

Sheet DATOS
A3: PRESUPUESO Nº: | B3: 110125
A4: CLIENTE: | B4: CLIENTE
A5: FECHA: | B5: =TODAY()
A6: COMERCIAL: | B6: MARIO
A7: REFERNCIA:
A8: DATOS FISCALES
A9: SOCIEDAD: | B9: CLIENTE
A10: NIF:
A11: DIRECCION:
A12: CORREO:
A13: PERSONA DE CONTACTO:
A14: TELEFONO:

Sheet PRESUPUESTO
A3: PRESU. Nº: | C3: =DATOS!B3 | AP3: PRESUPUESTO: | AR3: =C3
A4: CLIENTE: | C4: =DATOS!B4 | AP4: CLIENTE: | AR4: =C4
A5: FECHA: | C5: =DATOS!B5 | AP5: Con Fecha: | AR5: =C5 | AT5: COMERCIAL:
A6: COMERCIAL: | C6: =DATOS!B6 | AP6: Validez hasta: | AR6: =AR5+10 | AT6: REFERENCIA:
A7: REFERENCIA: | C7: =DATOS!B7
A8: DATOS DE TEJIDO | L8: TAMAÑO DEL ARTICULO A CONFECCIONAR | S8: MEDIDA TERMINADA | V8: DOBLADILLO | W8: MEDIDA CON DOBLAD. | Y8: ENCOG. (1/0) | Z8: MEDIDA CORTE | AB8: REDONDO (1/2) | AC8: EMPALME | AD8: REF. EMPALME | AE8: NUM. EMPALM | AF8: NUM. EMPALM. | AG8: CONFECCIÓN | AH8: COBRA SOBRANTE | AI8: TEJIDO | AJ8: FESTÓN (1/2) | AK8: PRECIO | AL8: COLOR | AM8: PICOS REDOND
A9: CANTIDAD | B9: MARGEN | C9: NOMBRE ARTICULO | D9: COLOR | E9: REF. 1 | F9: REF. 2 | G9: REF. 3 | I9: COSTE | J9: ANCHO PIEZA | K9: PRECIO VENTA | L9: ARTICULO (1/2/3/4/5/6) | M9: ANCHO | N9: LARGO | O9: REDONDA | P9: ALTO DE LA MESA | Q9: AÑADIR LARGO | R9: CAIDA MANTEL | S9: MEDIDA MESA | T9: ANCHO | U9: LARGO | V9: (1) Sencillo o Medida | W9: ANCHO | X9: LARGO | Y9: (1) Si (0) No | Z9: ANCHO | AA9: LARGO | AB9: (1) Si (2) No | AC9: (1) Si (2) No | AF9: SOLO SIN SON MENOS | AH9: (1) Si (2) No | AJ9: (1) Si (2) No | AK9: FESTÓN | AL9: FESTÓN | AM9: (1) Si (2) No | AP9: CINTA | AQ9: MESA | AR9: ARTICULO | AS9: MEDIDA USO | AT9: DESCRIPCION ARTICULO | AU9: COLOR | AV9: DOBLADILLO | AX9: MEDIDA DE CORTE | AY9: PRECIO UNITARIO | AZ9: CANTIDAD | BA9: TOTAL
A10: 0 | B10: 1 | D10: 1 | E10: =MATCH(C10,ARTICULOS!$F$10:$F$699,0) | F10: =+VLOOKUP(E10,ARTICULOS!$D$10:$I$699,6) | G10: =+F10&D10 | H10: =+MATCH(G10,COLORES!$E$7:$E$4394,0) | I10: =VLOOKUP(H10,COLORES!$A$7:$I$4394,8) | J10: =VLOOKUP(H10,COLORES!$A$7:$I$4394,9) | K10: =I10*(1+B10) | L10: 0 | M10: 0 | N10: 0 | O10: 0 | P10: 0 | Q10: 0 | S10: =IF(P10>0,IF(O10>0,"(/)"&O10&"*"&P10&IF(Q10>0,"+"&Q10,IF(Q10=0,"",Q10)),+M10&"*"&N10&"*"&P10&IF(Q10>0,"+"&Q10,IF(Q10=0,"",Q10))),"") | T10: =+IF(O10>0,O10+R10*2,M10+R10*2)+P10*2+Q10*2 | U10: =+IF(O10>0,O10+R10*2,N10+R10*2)+P10*2+Q10*2 | W10: =IF(V10=1,T10+5,T10+(V10*4)) | X10: =IF(V10=1,U10+5,U10+(V10*4)) | Y10: 0 | Z10: =IF(Y10=1,ROUNDUP(W10*(1+VLOOKUP(E10,ARTICULOS!$D$10:$H$699,5)),0),W10) | AA10: =IF(Y10=1,ROUNDUP(X10*(1+VLOOKUP(E10,ARTICULOS!$D$10:$H$699,4)),0),X10) | AB10: 2 | AD10: =IF(AC10=1,J10*100&Z10,"") | AE10: =IF(AC10=1,VLOOKUP(AD10,EMPALME!$C$2:$F$33,4),"") | AG10: =IF(L10=3,IF(V10=1,CONFECCION!$C$18,CONFECCION!$C$18*2),IF(V10=1,HLOOKUP(AA10,CONFECCION!$C$17:$AD$33,VLOOKUP(Z10,CONFECCION!$A$18:$B$33,2)-16),2*HLOOKUP(AA10,CONFECCION!$C$17:$AD$33,VLOOKUP(Z10,CONFECCION!$A$18:$B$33,2)-16)))*IF(AC10=1,3,1) | AI10: =IF(AC10=1,AA10/100*K10+IF(AF10>0,K10*(VLOOKUP(AD10,EMPALME!$C$2:$D$33,2)/100)/AF10,K10*(VLOOKUP(AD10,EMPALME!$C$2:$D$33,2)/100)/VLOOKUP(AD10,EMPALME!$C$2:$F$33,4)),IF(AH10=2,ROUND((K10*(AA10/100)-(I10/10)*INT((AA10/100)/0.55)*INT((J10-(Z10/100)*INT(J10/(Z10/100)))/0.55))/INT(J10/(Z10/100)),2),ROUND(K10*(AA10/100)/INT(J10/(Z10/100)),2))) | AJ10: 2 | AK10: =ROUND(IF(AJ10=2,0,((Z10*2)+(AA10*2))*CONFECCION!$B$35/100),2) | AM10: 2 | AQ10: =IF(S10=0,"",S10) | AR10: =IF(A10=0,"",VLOOKUP(L10,ARTICULOS!$A$10:$B$19,2)) | AS10: =IF(A10=0,"",T10&" * "&U10)&IF(AM10=1," PR","") | AT10: =IF(A10=0,"",VLOOKUP(E10,ARTICULOS!$D$10:$F$699,3)) | AU10: =IF(A10=0,"","c/ "&D10&" "&VLOOKUP(H10,COLORES!$A$7:$G$4394,7)) | AV10: =IF(A10=0,"",IF(V10=1,"Dobl. Sencillo","Dobl. "&V10&" cm.")) | AW10: =+IF(Y10=1,"SI","") | AX10: =IF(A10=0,"",IF(AB10=2,Z10&" * "&AA10,IF(Z10=AA10,"Redondo "&Z10&" * "&AA10,"Ovalado "&Z10&" * "&AA10))) | AY10: =IF(A10=0,"",AG10+AI10+AK10) | AZ10: =IF(A10=0,"",A10) | BA10: =IF(A10=0,"",ROUND(AY10*AZ10,2))
A11: 0 | B11: 1 | D11: 1 | E11: =MATCH(C11,ARTICULOS!$F$10:$F$699,0) | F11: =+VLOOKUP(E11,ARTICULOS!$D$10:$I$699,6) | G11: =+F11&D11 | H11: =+MATCH(G11,COLORES!$E$7:$E$4394,0) | I11: =VLOOKUP(H11,COLORES!$A$7:$I$4394,8) | J11: =VLOOKUP(H11,COLORES!$A$7:$I$4394,9) | K11: =I11*(1+B11) | L11: 0 | M11: 0 | N11: 0 | O11: 0 | P11: 0 | Q11: 0 | S11: =IF(P11>0,IF(O11>0,"(/)"&O11&"*"&P11&IF(Q11>0,"+"&Q11,IF(Q11=0,"",Q11)),+M11&"*"&N11&"*"&P11&IF(Q11>0,"+"&Q11,IF(Q11=0,"",Q11))),"") | T11: =+IF(O11>0,O11+R11*2,M11+R11*2)+P11*2+Q11*2 | U11: =+IF(O11>0,O11+R11*2,N11+R11*2)+P11*2+Q11*2 | W11: =IF(V11=1,T11+5,T11+(V11*4)) | X11: =IF(V11=1,U11+5,U11+(V11*4)) | Y11: 0 | Z11: =IF(Y11=1,ROUNDUP(W11*(1+VLOOKUP(E11,ARTICULOS!$D$10:$H$699,5)),0),W11) | AA11: =IF(Y11=1,ROUNDUP(X11*(1+VLOOKUP(E11,ARTICULOS!$D$10:$H$699,4)),0),X11) | AB11: 2 | AD11: =IF(AC11=1,J11*100&Z11,"") | AE11: =IF(AC11=1,VLOOKUP(AD11,EMPALME!$C$2:$F$33,4),"") | AG11: =IF(L11=3,IF(V11=1,CONFECCION!$C$18,CONFECCION!$C$18*2),IF(V11=1,HLOOKUP(AA11,CONFECCION!$C$17:$AD$33,VLOOKUP(Z11,CONFECCION!$A$18:$B$33,2)-16),2*HLOOKUP(AA11,CONFECCION!$C$17:$AD$33,VLOOKUP(Z11,CONFECCION!$A$18:$B$33,2)-16)))*IF(AC11=1,3,1) | AI11: =IF(AC11=1,AA11/100*K11+IF(AF11>0,K11*(VLOOKUP(AD11,EMPALME!$C$2:$D$33,2)/100)/AF11,K11*(VLOOKUP(AD11,EMPALME!$C$2:$D$33,2)/100)/VLOOKUP(AD11,EMPALME!$C$2:$F$33,4)),IF(AH11=2,ROUND((K11*(AA11/100)-(I11/10)*INT((AA11/100)/0.55)*INT((J11-(Z11/100)*INT(J11/(Z11/100)))/0.55))/INT(J11/(Z11/100)),2),ROUND(K11*(AA11/100)/INT(J11/(Z11/100)),2))) | AJ11: 2 | AK11: =ROUND(IF(AJ11=2,0,((Z11*2)+(AA11*2))*CONFECCION!$B$35/100),2) | AM11: 2 | AQ11: =IF(S11=0,"",S11) | AR11: =IF(A11=0,"",VLOOKUP(L11,ARTICULOS!$A$10:$B$19,2)) | AS11: =IF(A11=0,"",T11&" * "&U11)&IF(AM11=1," PR","") | AT11: =IF(A11=0,"",VLOOKUP(E11,ARTICULOS!$D$10:$F$699,3)) | AU11: =IF(A11=0,"","c/ "&D11&" "&VLOOKUP(H11,COLORES!$A$7:$G$4394,7)) | AV11: =IF(A11=0,"",IF(V11=1,"Dobl. Sencillo","Dobl. "&V11&" cm.")) | AW11: =+IF(Y11=1,"SI","") | AX11: =IF(A11=0,"",IF(AB11=2,Z11&" * "&AA11,IF(Z11=AA11,"Redondo "&Z11&" * "&AA11,"Ovalado "&Z11&" * "&AA11))) | AY11: =IF(A11=0,"",AG11+AI11+AK11) | AZ11: =IF(A11=0,"",A11) | BA11: =IF(A11=0,"",ROUND(AY11*AZ11,2))
A12: 0 | B12: 1 | D12: 1 | E12: =MATCH(C12,ARTICULOS!$F$10:$F$699,0) | F12: =+VLOOKUP(E12,ARTICULOS!$D$10:$I$699,6) | G12: =+F12&D12 | H12: =+MATCH(G12,COLORES!$E$7:$E$4394,0) | I12: =VLOOKUP(H12,COLORES!$A$7:$I$4394,8) | J12: =VLOOKUP(H12,COLORES!$A$7:$I$4394,9) | K12: =I12*(1+B12) | L12: 0 | M12: 0 | N12: 0 | O12: 0 | P12: 0 | Q12: 0 | S12: =IF(P12>0,IF(O12>0,"(/)"&O12&"*"&P12&IF(Q12>0,"+"&Q12,IF(Q12=0,"",Q12)),+M12&"*"&N12&"*"&P12&IF(Q12>0,"+"&Q12,IF(Q12=0,"",Q12))),"") | T12: =+IF(O12>0,O12+R12*2,M12+R12*2)+P12*2+Q12*2 | U12: =+IF(O12>0,O12+R12*2,N12+R12*2)+P12*2+Q12*2 | W12: =IF(V12=1,T12+5,T12+(V12*4)) | X12: =IF(V12=1,U12+5,U12+(V12*4)) | Y12: 0 | Z12: =IF(Y12=1,ROUNDUP(W12*(1+VLOOKUP(E12,ARTICULOS!$D$10:$H$699,5)),0),W12) | AA12: =IF(Y12=1,ROUNDUP(X12*(1+VLOOKUP(E12,ARTICULOS!$D$10:$H$699,4)),0),X12) | AB12: 2 | AD12: =IF(AC12=1,J12*100&Z12,"") | AE12: =IF(AC12=1,VLOOKUP(AD12,EMPALME!$C$2:$F$33,4),"") | AG12: =IF(L12=3,IF(V12=1,CONFECCION!$C$18,CONFECCION!$C$18*2),IF(V12=1,HLOOKUP(AA12,CONFECCION!$C$17:$AD$33,VLOOKUP(Z12,CONFECCION!$A$18:$B$33,2)-16),2*HLOOKUP(AA12,CONFECCION!$C$17:$AD$33,VLOOKUP(Z12,CONFECCION!$A$18:$B$33,2)-16)))*IF(AC12=1,3,1) | AI12: =IF(AC12=1,AA12/100*K12+IF(AF12>0,K12*(VLOOKUP(AD12,EMPALME!$C$2:$D$33,2)/100)/AF12,K12*(VLOOKUP(AD12,EMPALME!$C$2:$D$33,2)/100)/VLOOKUP(AD12,EMPALME!$C$2:$F$33,4)),IF(AH12=2,ROUND((K12*(AA12/100)-(I12/10)*INT((AA12/100)/0.55)*INT((J12-(Z12/100)*INT(J12/(Z12/100)))/0.55))/INT(J12/(Z12/100)),2),ROUND(K12*(AA12/100)/INT(J12/(Z12/100)),2))) | AJ12: 2 | AK12: =ROUND(IF(AJ12=2,0,((Z12*2)+(AA12*2))*CONFECCION!$B$35/100),2) | AM12: 2 | AQ12: =IF(S12=0,"",S12) | AR12: =IF(A12=0,"",VLOOKUP(L12,ARTICULOS!$A$10:$B$19,2)) | AS12: =IF(A12=0,"",T12&" * "&U12)&IF(AM12=1," PR","") | AT12: =IF(A12=0,"",VLOOKUP(E12,ARTICULOS!$D$10:$F$699,3)) | AU12: =IF(A12=0,"","c/ "&D12&" "&VLOOKUP(H12,COLORES!$A$7:$G$4394,7)) | AV12: =IF(A12=0,"",IF(V12=1,"Dobl. Sencillo","Dobl. "&V12&" cm.")) | AW12: =+IF(Y12=1,"SI","") | AX12: =IF(A12=0,"",IF(AB12=2,Z12&" * "&AA12,IF(Z12=AA12,"Redondo "&Z12&" * "&AA12,"Ovalado "&Z12&" * "&AA12))) | AY12: =IF(A12=0,"",AG12+AI12+AK12) | AZ12: =IF(A12=0,"",A12) | BA12: =IF(A12=0,"",ROUND(AY12*AZ12,2))
A13: 0 | B13: 1 | D13: 1 | E13: =MATCH(C13,ARTICULOS!$F$10:$F$699,0) | F13: =+VLOOKUP(E13,ARTICULOS!$D$10:$I$699,6) | G13: =+F13&D13 | H13: =+MATCH(G13,COLORES!$E$7:$E$4394,0) | I13: =VLOOKUP(H13,COLORES!$A$7:$I$4394,8) | J13: =VLOOKUP(H13,COLORES!$A$7:$I$4394,9) | K13: =I13*(1+B13) | L13: 0 | M13: 0 | N13: 0 | O13: 0 | P13: 0 | Q13: 0 | S13: =IF(P13>0,IF(O13>0,"(/)"&O13&"*"&P13&IF(Q13>0,"+"&Q13,IF(Q13=0,"",Q13)),+M13&"*"&N13&"*"&P13&IF(Q13>0,"+"&Q13,IF(Q13=0,"",Q13))),"") | T13: =+IF(O13>0,O13+R13*2,M13+R13*2)+P13*2+Q13*2 | U13: =+IF(O13>0,O13+R13*2,N13+R13*2)+P13*2+Q13*2 | W13: =IF(V13=1,T13+5,T13+(V13*4)) | X13: =IF(V13=1,U13+5,U13+(V13*4)) | Y13: 0 | Z13: =IF(Y13=1,ROUNDUP(W13*(1+VLOOKUP(E13,ARTICULOS!$D$10:$H$699,5)),0),W13) | AA13: =IF(Y13=1,ROUNDUP(X13*(1+VLOOKUP(E13,ARTICULOS!$D$10:$H$699,4)),0),X13) | AB13: 2 | AD13: =IF(AC13=1,J13*100&Z13,"") | AE13: =IF(AC13=1,VLOOKUP(AD13,EMPALME!$C$2:$F$33,4),"") | AG13: =IF(L13=3,IF(V13=1,CONFECCION!$C$18,CONFECCION!$C$18*2),IF(V13=1,HLOOKUP(AA13,CONFECCION!$C$17:$AD$33,VLOOKUP(Z13,CONFECCION!$A$18:$B$33,2)-16),2*HLOOKUP(AA13,CONFECCION!$C$17:$AD$33,VLOOKUP(Z13,CONFECCION!$A$18:$B$33,2)-16)))*IF(AC13=1,3,1) | AI13: =IF(AC13=1,AA13/100*K13+IF(AF13>0,K13*(VLOOKUP(AD13,EMPALME!$C$2:$D$33,2)/100)/AF13,K13*(VLOOKUP(AD13,EMPALME!$C$2:$D$33,2)/100)/VLOOKUP(AD13,EMPALME!$C$2:$F$33,4)),IF(AH13=2,ROUND((K13*(AA13/100)-(I13/10)*INT((AA13/100)/0.55)*INT((J13-(Z13/100)*INT(J13/(Z13/100)))/0.55))/INT(J13/(Z13/100)),2),ROUND(K13*(AA13/100)/INT(J13/(Z13/100)),2))) | AJ13: 2 | AK13: =ROUND(IF(AJ13=2,0,((Z13*2)+(AA13*2))*CONFECCION!$B$35/100),2) | AM13: 2 | AQ13: =IF(S13=0,"",S13) | AR13: =IF(A13=0,"",VLOOKUP(L13,ARTICULOS!$A$10:$B$19,2)) | AS13: =IF(A13=0,"",T13&" * "&U13)&IF(AM13=1," PR","") | AT13: =IF(A13=0,"",VLOOKUP(E13,ARTICULOS!$D$10:$F$699,3)) | AU13: =IF(A13=0,"","c/ "&D13&" "&VLOOKUP(H13,COLORES!$A$7:$G$4394,7)) | AV13: =IF(A13=0,"",IF(V13=1,"Dobl. Sencillo","Dobl. "&V13&" cm.")) | AW13: =+IF(Y13=1,"SI","") | AX13: =IF(A13=0,"",IF(AB13=2,Z13&" * "&AA13,IF(Z13=AA13,"Redondo "&Z13&" * "&AA13,"Ovalado "&Z13&" * "&AA13))) | AY13: =IF(A13=0,"",AG13+AI13+AK13) | AZ13: =IF(A13=0,"",A13) | BA13: =IF(A13=0,"",ROUND(AY13*AZ13,2))
A14: 0 | B14: 1 | D14: 1 | E14: =MATCH(C14,ARTICULOS!$F$10:$F$699,0) | F14: =+VLOOKUP(E14,ARTICULOS!$D$10:$I$699,6) | G14: =+F14&D14 | H14: =+MATCH(G14,COLORES!$E$7:$E$4394,0) | I14: =VLOOKUP(H14,COLORES!$A$7:$I$4394,8) | J14: =VLOOKUP(H14,COLORES!$A$7:$I$4394,9) | K14: =I14*(1+B14) | L14: 0 | M14: 0 | N14: 0 | O14: 0 | P14: 0 | Q14: 0 | S14: =IF(P14>0,IF(O14>0,"(/)"&O14&"*"&P14&IF(Q14>0,"+"&Q14,IF(Q14=0,"",Q14)),+M14&"*"&N14&"*"&P14&IF(Q14>0,"+"&Q14,IF(Q14=0,"",Q14))),"") | T14: =+IF(O14>0,O14+R14*2,M14+R14*2)+P14*2+Q14*2 | U14: =+IF(O14>0,O14+R14*2,N14+R14*2)+P14*2+Q14*2 | W14: =IF(V14=1,T14+5,T14+(V14*4)) | X14: =IF(V14=1,U14+5,U14+(V14*4)) | Y14: 0 | Z14: =IF(Y14=1,ROUNDUP(W14*(1+VLOOKUP(E14,ARTICULOS!$D$10:$H$699,5)),0),W14) | AA14: =IF(Y14=1,ROUNDUP(X14*(1+VLOOKUP(E14,ARTICULOS!$D$10:$H$699,4)),0),X14) | AB14: 2 | AD14: =IF(AC14=1,J14*100&Z14,"") | AE14: =IF(AC14=1,VLOOKUP(AD14,EMPALME!$C$2:$F$33,4),"") | AG14: =IF(L14=3,IF(V14=1,CONFECCION!$C$18,CONFECCION!$C$18*2),IF(V14=1,HLOOKUP(AA14,CONFECCION!$C$17:$AD$33,VLOOKUP(Z14,CONFECCION!$A$18:$B$33,2)-16),2*HLOOKUP(AA14,CONFECCION!$C$17:$AD$33,VLOOKUP(Z14,CONFECCION!$A$18:$B$33,2)-16)))*IF(AC14=1,3,1) | AI14: =IF(AC14=1,AA14/100*K14+IF(AF14>0,K14*(VLOOKUP(AD14,EMPALME!$C$2:$D$33,2)/100)/AF14,K14*(VLOOKUP(AD14,EMPALME!$C$2:$D$33,2)/100)/VLOOKUP(AD14,EMPALME!$C$2:$F$33,4)),IF(AH14=2,ROUND((K14*(AA14/100)-(I14/10)*INT((AA14/100)/0.55)*INT((J14-(Z14/100)*INT(J14/(Z14/100)))/0.55))/INT(J14/(Z14/100)),2),ROUND(K14*(AA14/100)/INT(J14/(Z14/100)),2))) | AJ14: 2 | AK14: =ROUND(IF(AJ14=2,0,((Z14*2)+(AA14*2))*CONFECCION!$B$35/100),2) | AM14: 2 | AQ14: =IF(S14=0,"",S14) | AR14: =IF(A14=0,"",VLOOKUP(L14,ARTICULOS!$A$10:$B$19,2)) | AS14: =IF(A14=0,"",T14&" * "&U14)&IF(AM14=1," PR","") | AT14: =IF(A14=0,"",VLOOKUP(E14,ARTICULOS!$D$10:$F$699,3)) | AU14: =IF(A14=0,"","c/ "&D14&" "&VLOOKUP(H14,COLORES!$A$7:$G$4394,7)) | AV14: =IF(A14=0,"",IF(V14=1,"Dobl. Sencillo","Dobl. "&V14&" cm.")) | AW14: =+IF(Y14=1,"SI","") | AX14: =IF(A14=0,"",IF(AB14=2,Z14&" * "&AA14,IF(Z14=AA14,"Redondo "&Z14&" * "&AA14,"Ovalado "&Z14&" * "&AA14))) | AY14: =IF(A14=0,"",AG14+AI14+AK14) | AZ14: =IF(A14=0,"",A14) | BA14: =IF(A14=0,"",ROUND(AY14*AZ14,2))
A15: 0 | B15: 1 | D15: 1 | E15: =MATCH(C15,ARTICULOS!$F$10:$F$699,0) | F15: =+VLOOKUP(E15,ARTICULOS!$D$10:$I$699,6) | G15: =+F15&D15 | H15: =+MATCH(G15,COLORES!$E$7:$E$4394,0) | I15: =VLOOKUP(H15,COLORES!$A$7:$I$4394,8) | J15: =VLOOKUP(H15,COLORES!$A$7:$I$4394,9) | K15: =I15*(1+B15) | L15: 0 | M15: 0 | N15: 0 | O15: 0 | P15: 0 | Q15: 0 | S15: =IF(P15>0,IF(O15>0,"(/)"&O15&"*"&P15&IF(Q15>0,"+"&Q15,IF(Q15=0,"",Q15)),+M15&"*"&N15&"*"&P15&IF(Q15>0,"+"&Q15,IF(Q15=0,"",Q15))),"") | T15: =+IF(O15>0,O15+R15*2,M15+R15*2)+P15*2+Q15*2 | U15: =+IF(O15>0,O15+R15*2,N15+R15*2)+P15*2+Q15*2 | W15: =IF(V15=1,T15+5,T15+(V15*4)) | X15: =IF(V15=1,U15+5,U15+(V15*4)) | Y15: 0 | Z15: =IF(Y15=1,ROUNDUP(W15*(1+VLOOKUP(E15,ARTICULOS!$D$10:$H$699,5)),0),W15) | AA15: =IF(Y15=1,ROUNDUP(X15*(1+VLOOKUP(E15,ARTICULOS!$D$10:$H$699,4)),0),X15) | AB15: 2 | AD15: =IF(AC15=1,J15*100&Z15,"") | AE15: =IF(AC15=1,VLOOKUP(AD15,EMPALME!$C$2:$F$33,4),"") | AG15: =IF(L15=3,IF(V15=1,CONFECCION!$C$18,CONFECCION!$C$18*2),IF(V15=1,HLOOKUP(AA15,CONFECCION!$C$17:$AD$33,VLOOKUP(Z15,CONFECCION!$A$18:$B$33,2)-16),2*HLOOKUP(AA15,CONFECCION!$C$17:$AD$33,VLOOKUP(Z15,CONFECCION!$A$18:$B$33,2)-16)))*IF(AC15=1,3,1) | AI15: =IF(AC15=1,AA15/100*K15+IF(AF15>0,K15*(VLOOKUP(AD15,EMPALME!$C$2:$D$33,2)/100)/AF15,K15*(VLOOKUP(AD15,EMPALME!$C$2:$D$33,2)/100)/VLOOKUP(AD15,EMPALME!$C$2:$F$33,4)),IF(AH15=2,ROUND((K15*(AA15/100)-(I15/10)*INT((AA15/100)/0.55)*INT((J15-(Z15/100)*INT(J15/(Z15/100)))/0.55))/INT(J15/(Z15/100)),2),ROUND(K15*(AA15/100)/INT(J15/(Z15/100)),2))) | AJ15: 2 | AK15: =ROUND(IF(AJ15=2,0,((Z15*2)+(AA15*2))*CONFECCION!$B$35/100),2) | AM15: 2 | AQ15: =IF(S15=0,"",S15) | AR15: =IF(A15=0,"",VLOOKUP(L15,ARTICULOS!$A$10:$B$19,2)) | AS15: =IF(A15=0,"",T15&" * "&U15)&IF(AM15=1," PR","") | AT15: =IF(A15=0,"",VLOOKUP(E15,ARTICULOS!$D$10:$F$699,3)) | AU15: =IF(A15=0,"","c/ "&D15&" "&VLOOKUP(H15,COLORES!$A$7:$G$4394,7)) | AV15: =IF(A15=0,"",IF(V15=1,"Dobl. Sencillo","Dobl. "&V15&" cm.")) | AW15: =+IF(Y15=1,"SI","") | AX15: =IF(A15=0,"",IF(AB15=2,Z15&" * "&AA15,IF(Z15=AA15,"Redondo "&Z15&" * "&AA15,"Ovalado "&Z15&" * "&AA15))) | AY15: =IF(A15=0,"",AG15+AI15+AK15) | AZ15: =IF(A15=0,"",A15) | BA15: =IF(A15=0,"",ROUND(AY15*AZ15,2))
A16: 0 | B16: 1 | D16: 1 | E16: =MATCH(C16,ARTICULOS!$F$10:$F$699,0) | F16: =+VLOOKUP(E16,ARTICULOS!$D$10:$I$699,6) | G16: =+F16&D16 | H16: =+MATCH(G16,COLORES!$E$7:$E$4394,0) | I16: =VLOOKUP(H16,COLORES!$A$7:$I$4394,8) | J16: =VLOOKUP(H16,COLORES!$A$7:$I$4394,9) | K16: =I16*(1+B16) | L16: 0 | M16: 0 | N16: 0 | O16: 0 | P16: 0 | Q16: 0 | S16: =IF(P16>0,IF(O16>0,"(/)"&O16&"*"&P16&IF(Q16>0,"+"&Q16,IF(Q16=0,"",Q16)),+M16&"*"&N16&"*"&P16&IF(Q16>0,"+"&Q16,IF(Q16=0,"",Q16))),"") | T16: =+IF(O16>0,O16+R16*2,M16+R16*2)+P16*2+Q16*2 | U16: =+IF(O16>0,O16+R16*2,N16+R16*2)+P16*2+Q16*2 | W16: =IF(V16=1,T16+5,T16+(V16*4)) | X16: =IF(V16=1,U16+5,U16+(V16*4)) | Y16: 0 | Z16: =IF(Y16=1,ROUNDUP(W16*(1+VLOOKUP(E16,ARTICULOS!$D$10:$H$699,5)),0),W16) | AA16: =IF(Y16=1,ROUNDUP(X16*(1+VLOOKUP(E16,ARTICULOS!$D$10:$H$699,4)),0),X16) | AB16: 2 | AD16: =IF(AC16=1,J16*100&Z16,"") | AE16: =IF(AC16=1,VLOOKUP(AD16,EMPALME!$C$2:$F$33,4),"") | AG16: =IF(L16=3,IF(V16=1,CONFECCION!$C$18,CONFECCION!$C$18*2),IF(V16=1,HLOOKUP(AA16,CONFECCION!$C$17:$AD$33,VLOOKUP(Z16,CONFECCION!$A$18:$B$33,2)-16),2*HLOOKUP(AA16,CONFECCION!$C$17:$AD$33,VLOOKUP(Z16,CONFECCION!$A$18:$B$33,2)-16)))*IF(AC16=1,3,1) | AI16: =IF(AC16=1,AA16/100*K16+IF(AF16>0,K16*(VLOOKUP(AD16,EMPALME!$C$2:$D$33,2)/100)/AF16,K16*(VLOOKUP(AD16,EMPALME!$C$2:$D$33,2)/100)/VLOOKUP(AD16,EMPALME!$C$2:$F$33,4)),IF(AH16=2,ROUND((K16*(AA16/100)-(I16/10)*INT((AA16/100)/0.55)*INT((J16-(Z16/100)*INT(J16/(Z16/100)))/0.55))/INT(J16/(Z16/100)),2),ROUND(K16*(AA16/100)/INT(J16/(Z16/100)),2))) | AJ16: 2 | AK16: =ROUND(IF(AJ16=2,0,((Z16*2)+(AA16*2))*CONFECCION!$B$35/100),2) | AM16: 2 | AQ16: =IF(S16=0,"",S16) | AR16: =IF(A16=0,"",VLOOKUP(L16,ARTICULOS!$A$10:$B$19,2)) | AS16: =IF(A16=0,"",T16&" * "&U16)&IF(AM16=1," PR","") | AT16: =IF(A16=0,"",VLOOKUP(E16,ARTICULOS!$D$10:$F$699,3)) | AU16: =IF(A16=0,"","c/ "&D16&" "&VLOOKUP(H16,COLORES!$A$7:$G$4394,7)) | AV16: =IF(A16=0,"",IF(V16=1,"Dobl. Sencillo","Dobl. "&V16&" cm.")) | AW16: =+IF(Y16=1,"SI","") | AX16: =IF(A16=0,"",IF(AB16=2,Z16&" * "&AA16,IF(Z16=AA16,"Redondo "&Z16&" * "&AA16,"Ovalado "&Z16&" * "&AA16))) | AY16: =IF(A16=0,"",AG16+AI16+AK16) | AZ16: =IF(A16=0,"",A16) | BA16: =IF(A16=0,"",ROUND(AY16*AZ16,2))
A17: 0 | B17: 1 | D17: 1 | E17: =MATCH(C17,ARTICULOS!$F$10:$F$699,0) | F17: =+VLOOKUP(E17,ARTICULOS!$D$10:$I$699,6) | G17: =+F17&D17 | H17: =+MATCH(G17,COLORES!$E$7:$E$4394,0) | I17: =VLOOKUP(H17,COLORES!$A$7:$I$4394,8) | J17: =VLOOKUP(H17,COLORES!$A$7:$I$4394,9) | K17: =I17*(1+B17) | L17: 0 | M17: 0 | N17: 0 | O17: 0 | P17: 0 | Q17: 0 | S17: =IF(P17>0,IF(O17>0,"(/)"&O17&"*"&P17&IF(Q17>0,"+"&Q17,IF(Q17=0,"",Q17)),+M17&"*"&N17&"*"&P17&IF(Q17>0,"+"&Q17,IF(Q17=0,"",Q17))),"") | T17: =+IF(O17>0,O17+R17*2,M17+R17*2)+P17*2+Q17*2 | U17: =+IF(O17>0,O17+R17*2,N17+R17*2)+P17*2+Q17*2 | W17: =IF(V17=1,T17+5,T17+(V17*4)) | X17: =IF(V17=1,U17+5,U17+(V17*4)) | Y17: 0 | Z17: =IF(Y17=1,ROUNDUP(W17*(1+VLOOKUP(E17,ARTICULOS!$D$10:$H$699,5)),0),W17) | AA17: =IF(Y17=1,ROUNDUP(X17*(1+VLOOKUP(E17,ARTICULOS!$D$10:$H$699,4)),0),X17) | AB17: 2 | AD17: =IF(AC17=1,J17*100&Z17,"") | AE17: =IF(AC17=1,VLOOKUP(AD17,EMPALME!$C$2:$F$33,4),"") | AG17: =IF(L17=3,IF(V17=1,CONFECCION!$C$18,CONFECCION!$C$18*2),IF(V17=1,HLOOKUP(AA17,CONFECCION!$C$17:$AD$33,VLOOKUP(Z17,CONFECCION!$A$18:$B$33,2)-16),2*HLOOKUP(AA17,CONFECCION!$C$17:$AD$33,VLOOKUP(Z17,CONFECCION!$A$18:$B$33,2)-16)))*IF(AC17=1,3,1) | AI17: =IF(AC17=1,AA17/100*K17+IF(AF17>0,K17*(VLOOKUP(AD17,EMPALME!$C$2:$D$33,2)/100)/AF17,K17*(VLOOKUP(AD17,EMPALME!$C$2:$D$33,2)/100)/VLOOKUP(AD17,EMPALME!$C$2:$F$33,4)),IF(AH17=2,ROUND((K17*(AA17/100)-(I17/10)*INT((AA17/100)/0.55)*INT((J17-(Z17/100)*INT(J17/(Z17/100)))/0.55))/INT(J17/(Z17/100)),2),ROUND(K17*(AA17/100)/INT(J17/(Z17/100)),2))) | AJ17: 2 | AK17: =ROUND(IF(AJ17=2,0,((Z17*2)+(AA17*2))*CONFECCION!$B$35/100),2) | AM17: 2 | AQ17: =IF(S17=0,"",S17) | AR17: =IF(A17=0,"",VLOOKUP(L17,ARTICULOS!$A$10:$B$19,2)) | AS17: =IF(A17=0,"",T17&" * "&U17)&IF(AM17=1," PR","") | AT17: =IF(A17=0,"",VLOOKUP(E17,ARTICULOS!$D$10:$F$699,3)) | AU17: =IF(A17=0,"","c/ "&D17&" "&VLOOKUP(H17,COLORES!$A$7:$G$4394,7)) | AV17: =IF(A17=0,"",IF(V17=1,"Dobl. Sencillo","Dobl. "&V17&" cm.")) | AW17: =+IF(Y17=1,"SI","") | AX17: =IF(A17=0,"",IF(AB17=2,Z17&" * "&AA17,IF(Z17=AA17,"Redondo "&Z17&" * "&AA17,"Ovalado "&Z17&" * "&AA17))) | AY17: =IF(A17=0,"",AG17+AI17+AK17) | AZ17: =IF(A17=0,"",A17) | BA17: =IF(A17=0,"",ROUND(AY17*AZ17,2))
A18: 0 | B18: 1 | D18: 1 | E18: =MATCH(C18,ARTICULOS!$F$10:$F$699,0) | F18: =+VLOOKUP(E18,ARTICULOS!$D$10:$I$699,6) | G18: =+F18&D18 | H18: =+MATCH(G18,COLORES!$E$7:$E$4394,0) | I18: =VLOOKUP(H18,COLORES!$A$7:$I$4394,8) | J18: =VLOOKUP(H18,COLORES!$A$7:$I$4394,9) | K18: =I18*(1+B18) | L18: 0 | M18: 0 | N18: 0 | O18: 0 | P18: 0 | Q18: 0 | S18: =IF(P18>0,IF(O18>0,"(/)"&O18&"*"&P18&IF(Q18>0,"+"&Q18,IF(Q18=0,"",Q18)),+M18&"*"&N18&"*"&P18&IF(Q18>0,"+"&Q18,IF(Q18=0,"",Q18))),"") | T18: =+IF(O18>0,O18+R18*2,M18+R18*2)+P18*2+Q18*2 | U18: =+IF(O18>0,O18+R18*2,N18+R18*2)+P18*2+Q18*2 | W18: =IF(V18=1,T18+5,T18+(V18*4)) | X18: =IF(V18=1,U18+5,U18+(V18*4)) | Y18: 0 | Z18: =IF(Y18=1,ROUNDUP(W18*(1+VLOOKUP(E18,ARTICULOS!$D$10:$H$699,5)),0),W18) | AA18: =IF(Y18=1,ROUNDUP(X18*(1+VLOOKUP(E18,ARTICULOS!$D$10:$H$699,4)),0),X18) | AB18: 2 | AD18: =IF(AC18=1,J18*100&Z18,"") | AE18: =IF(AC18=1,VLOOKUP(AD18,EMPALME!$C$2:$F$33,4),"") | AG18: =IF(L18=3,IF(V18=1,CONFECCION!$C$18,CONFECCION!$C$18*2),IF(V18=1,HLOOKUP(AA18,CONFECCION!$C$17:$AD$33,VLOOKUP(Z18,CONFECCION!$A$18:$B$33,2)-16),2*HLOOKUP(AA18,CONFECCION!$C$17:$AD$33,VLOOKUP(Z18,CONFECCION!$A$18:$B$33,2)-16)))*IF(AC18=1,3,1) | AI18: =IF(AC18=1,AA18/100*K18+IF(AF18>0,K18*(VLOOKUP(AD18,EMPALME!$C$2:$D$33,2)/100)/AF18,K18*(VLOOKUP(AD18,EMPALME!$C$2:$D$33,2)/100)/VLOOKUP(AD18,EMPALME!$C$2:$F$33,4)),IF(AH18=2,ROUND((K18*(AA18/100)-(I18/10)*INT((AA18/100)/0.55)*INT((J18-(Z18/100)*INT(J18/(Z18/100)))/0.55))/INT(J18/(Z18/100)),2),ROUND(K18*(AA18/100)/INT(J18/(Z18/100)),2))) | AJ18: 2 | AK18: =ROUND(IF(AJ18=2,0,((Z18*2)+(AA18*2))*CONFECCION!$B$35/100),2) | AM18: 2 | AQ18: =IF(S18=0,"",S18) | AR18: =IF(A18=0,"",VLOOKUP(L18,ARTICULOS!$A$10:$B$19,2)) | AS18: =IF(A18=0,"",T18&" * "&U18)&IF(AM18=1," PR","") | AT18: =IF(A18=0,"",VLOOKUP(E18,ARTICULOS!$D$10:$F$699,3)) | AU18: =IF(A18=0,"","c/ "&D18&" "&VLOOKUP(H18,COLORES!$A$7:$G$4394,7)) | AV18: =IF(A18=0,"",IF(V18=1,"Dobl. Sencillo","Dobl. "&V18&" cm.")) | AW18: =+IF(Y18=1,"SI","") | AX18: =IF(A18=0,"",IF(AB18=2,Z18&" * "&AA18,IF(Z18=AA18,"Redondo "&Z18&" * "&AA18,"Ovalado "&Z18&" * "&AA18))) | AY18: =IF(A18=0,"",AG18+AI18+AK18) | AZ18: =IF(A18=0,"",A18) | BA18: =IF(A18=0,"",ROUND(AY18*AZ18,2))
A19: 0 | B19: 1 | D19: 1 | E19: =MATCH(C19,ARTICULOS!$F$10:$F$699,0) | F19: =+VLOOKUP(E19,ARTICULOS!$D$10:$I$699,6) | G19: =+F19&D19 | H19: =+MATCH(G19,COLORES!$E$7:$E$4394,0) | I19: =VLOOKUP(H19,COLORES!$A$7:$I$4394,8) | J19: =VLOOKUP(H19,COLORES!$A$7:$I$4394,9) | K19: =I19*(1+B19) | L19: 0 | M19: 0 | N19: 0 | O19: 0 | P19: 0 | Q19: 0 | S19: =IF(P19>0,IF(O19>0,"(/)"&O19&"*"&P19&IF(Q19>0,"+"&Q19,IF(Q19=0,"",Q19)),+M19&"*"&N19&"*"&P19&IF(Q19>0,"+"&Q19,IF(Q19=0,"",Q19))),"") | T19: =+IF(O19>0,O19+R19*2,M19+R19*2)+P19*2+Q19*2 | U19: =+IF(O19>0,O19+R19*2,N19+R19*2)+P19*2+Q19*2 | W19: =IF(V19=1,T19+5,T19+(V19*4)) | X19: =IF(V19=1,U19+5,U19+(V19*4)) | Y19: 0 | Z19: =IF(Y19=1,ROUNDUP(W19*(1+VLOOKUP(E19,ARTICULOS!$D$10:$H$699,5)),0),W19) | AA19: =IF(Y19=1,ROUNDUP(X19*(1+VLOOKUP(E19,ARTICULOS!$D$10:$H$699,4)),0),X19) | AB19: 2 | AD19: =IF(AC19=1,J19*100&Z19,"") | AE19: =IF(AC19=1,VLOOKUP(AD19,EMPALME!$C$2:$F$33,4),"") | AG19: =IF(L19=3,IF(V19=1,CONFECCION!$C$18,CONFECCION!$C$18*2),IF(V19=1,HLOOKUP(AA19,CONFECCION!$C$17:$AD$33,VLOOKUP(Z19,CONFECCION!$A$18:$B$33,2)-16),2*HLOOKUP(AA19,CONFECCION!$C$17:$AD$33,VLOOKUP(Z19,CONFECCION!$A$18:$B$33,2)-16)))*IF(AC19=1,3,1) | AI19: =IF(AC19=1,AA19/100*K19+IF(AF19>0,K19*(VLOOKUP(AD19,EMPALME!$C$2:$D$33,2)/100)/AF19,K19*(VLOOKUP(AD19,EMPALME!$C$2:$D$33,2)/100)/VLOOKUP(AD19,EMPALME!$C$2:$F$33,4)),IF(AH19=2,ROUND((K19*(AA19/100)-(I19/10)*INT((AA19/100)/0.55)*INT((J19-(Z19/100)*INT(J19/(Z19/100)))/0.55))/INT(J19/(Z19/100)),2),ROUND(K19*(AA19/100)/INT(J19/(Z19/100)),2))) | AJ19: 2 | AK19: =ROUND(IF(AJ19=2,0,((Z19*2)+(AA19*2))*CONFECCION!$B$35/100),2) | AM19: 2 | AQ19: =IF(S19=0,"",S19) | AR19: =IF(A19=0,"",VLOOKUP(L19,ARTICULOS!$A$10:$B$19,2)) | AS19: =IF(A19=0,"",T19&" * "&U19)&IF(AM19=1," PR","") | AT19: =IF(A19=0,"",VLOOKUP(E19,ARTICULOS!$D$10:$F$699,3)) | AU19: =IF(A19=0,"","c/ "&D19&" "&VLOOKUP(H19,COLORES!$A$7:$G$4394,7)) | AV19: =IF(A19=0,"",IF(V19=1,"Dobl. Sencillo","Dobl. "&V19&" cm.")) | AW19: =+IF(Y19=1,"SI","") | AX19: =IF(A19=0,"",IF(AB19=2,Z19&" * "&AA19,IF(Z19=AA19,"Redondo "&Z19&" * "&AA19,"Ovalado "&Z19&" * "&AA19))) | AY19: =IF(A19=0,"",AG19+AI19+AK19) | AZ19: =IF(A19=0,"",A19) | BA19: =IF(A19=0,"",ROUND(AY19*AZ19,2))
A20: 0 | B20: 1 | D20: 1 | E20: =MATCH(C20,ARTICULOS!$F$10:$F$699,0) | F20: =+VLOOKUP(E20,ARTICULOS!$D$10:$I$699,6) | G20: =+F20&D20 | H20: =+MATCH(G20,COLORES!$E$7:$E$4394,0) | I20: =VLOOKUP(H20,COLORES!$A$7:$I$4394,8) | J20: =VLOOKUP(H20,COLORES!$A$7:$I$4394,9) | K20: =I20*(1+B20) | L20: 0 | M20: 0 | N20: 0 | O20: 0 | P20: 0 | Q20: 0 | S20: =IF(P20>0,IF(O20>0,"(/)"&O20&"*"&P20&IF(Q20>0,"+"&Q20,IF(Q20=0,"",Q20)),+M20&"*"&N20&"*"&P20&IF(Q20>0,"+"&Q20,IF(Q20=0,"",Q20))),"") | T20: =+IF(O20>0,O20+R20*2,M20+R20*2)+P20*2+Q20*2 | U20: =+IF(O20>0,O20+R20*2,N20+R20*2)+P20*2+Q20*2 | W20: =IF(V20=1,T20+5,T20+(V20*4)) | X20: =IF(V20=1,U20+5,U20+(V20*4)) | Y20: 0 | Z20: =IF(Y20=1,ROUNDUP(W20*(1+VLOOKUP(E20,ARTICULOS!$D$10:$H$699,5)),0),W20) | AA20: =IF(Y20=1,ROUNDUP(X20*(1+VLOOKUP(E20,ARTICULOS!$D$10:$H$699,4)),0),X20) | AB20: 2 | AD20: =IF(AC20=1,J20*100&Z20,"") | AE20: =IF(AC20=1,VLOOKUP(AD20,EMPALME!$C$2:$F$33,4),"") | AG20: =IF(L20=3,IF(V20=1,CONFECCION!$C$18,CONFECCION!$C$18*2),IF(V20=1,HLOOKUP(AA20,CONFECCION!$C$17:$AD$33,VLOOKUP(Z20,CONFECCION!$A$18:$B$33,2)-16),2*HLOOKUP(AA20,CONFECCION!$C$17:$AD$33,VLOOKUP(Z20,CONFECCION!$A$18:$B$33,2)-16)))*IF(AC20=1,3,1) | AI20: =IF(AC20=1,AA20/100*K20+IF(AF20>0,K20*(VLOOKUP(AD20,EMPALME!$C$2:$D$33,2)/100)/AF20,K20*(VLOOKUP(AD20,EMPALME!$C$2:$D$33,2)/100)/VLOOKUP(AD20,EMPALME!$C$2:$F$33,4)),IF(AH20=2,ROUND((K20*(AA20/100)-(I20/10)*INT((AA20/100)/0.55)*INT((J20-(Z20/100)*INT(J20/(Z20/100)))/0.55))/INT(J20/(Z20/100)),2),ROUND(K20*(AA20/100)/INT(J20/(Z20/100)),2))) | AJ20: 2 | AK20: =ROUND(IF(AJ20=2,0,((Z20*2)+(AA20*2))*CONFECCION!$B$35/100),2) | AM20: 2 | AQ20: =IF(S20=0,"",S20) | AR20: =IF(A20=0,"",VLOOKUP(L20,ARTICULOS!$A$10:$B$19,2)) | AS20: =IF(A20=0,"",T20&" * "&U20)&IF(AM20=1," PR","") | AT20: =IF(A20=0,"",VLOOKUP(E20,ARTICULOS!$D$10:$F$699,3)) | AU20: =IF(A20=0,"","c/ "&D20&" "&VLOOKUP(H20,COLORES!$A$7:$G$4394,7)) | AV20: =IF(A20=0,"",IF(V20=1,"Dobl. Sencillo","Dobl. "&V20&" cm.")) | AW20: =+IF(Y20=1,"SI","") | AX20: =IF(A20=0,"",IF(AB20=2,Z20&" * "&AA20,IF(Z20=AA20,"Redondo "&Z20&" * "&AA20,"Ovalado "&Z20&" * "&AA20))) | AY20: =IF(A20=0,"",AG20+AI20+AK20) | AZ20: =IF(A20=0,"",A20) | BA20: =IF(A20=0,"",ROUND(AY20*AZ20,2))
A21: 0 | B21: 1 | D21: 1 | E21: =MATCH(C21,ARTICULOS!$F$10:$F$699,0) | F21: =+VLOOKUP(E21,ARTICULOS!$D$10:$I$699,6) | G21: =+F21&D21 | H21: =+MATCH(G21,COLORES!$E$7:$E$4394,0) | I21: =VLOOKUP(H21,COLORES!$A$7:$I$4394,8) | J21: =VLOOKUP(H21,COLORES!$A$7:$I$4394,9) | K21: =I21*(1+B21) | L21: 0 | M21: 0 | N21: 0 | O21: 0 | P21: 0 | Q21: 0 | S21: =IF(P21>0,IF(O21>0,"(/)"&O21&"*"&P21&IF(Q21>0,"+"&Q21,IF(Q21=0,"",Q21)),+M21&"*"&N21&"*"&P21&IF(Q21>0,"+"&Q21,IF(Q21=0,"",Q21))),"") | T21: =+IF(O21>0,O21+R21*2,M21+R21*2)+P21*2+Q21*2 | U21: =+IF(O21>0,O21+R21*2,N21+R21*2)+P21*2+Q21*2 | W21: =IF(V21=1,T21+5,T21+(V21*4)) | X21: =IF(V21=1,U21+5,U21+(V21*4)) | Y21: 0 | Z21: =IF(Y21=1,ROUNDUP(W21*(1+VLOOKUP(E21,ARTICULOS!$D$10:$H$699,5)),0),W21) | AA21: =IF(Y21=1,ROUNDUP(X21*(1+VLOOKUP(E21,ARTICULOS!$D$10:$H$699,4)),0),X21) | AB21: 2 | AD21: =IF(AC21=1,J21*100&Z21,"") | AE21: =IF(AC21=1,VLOOKUP(AD21,EMPALME!$C$2:$F$33,4),"") | AG21: =IF(L21=3,IF(V21=1,CONFECCION!$C$18,CONFECCION!$C$18*2),IF(V21=1,HLOOKUP(AA21,CONFECCION!$C$17:$AD$33,VLOOKUP(Z21,CONFECCION!$A$18:$B$33,2)-16),2*HLOOKUP(AA21,CONFECCION!$C$17:$AD$33,VLOOKUP(Z21,CONFECCION!$A$18:$B$33,2)-16)))*IF(AC21=1,3,1) | AI21: =IF(AC21=1,AA21/100*K21+IF(AF21>0,K21*(VLOOKUP(AD21,EMPALME!$C$2:$D$33,2)/100)/AF21,K21*(VLOOKUP(AD21,EMPALME!$C$2:$D$33,2)/100)/VLOOKUP(AD21,EMPALME!$C$2:$F$33,4)),IF(AH21=2,ROUND((K21*(AA21/100)-(I21/10)*INT((AA21/100)/0.55)*INT((J21-(Z21/100)*INT(J21/(Z21/100)))/0.55))/INT(J21/(Z21/100)),2),ROUND(K21*(AA21/100)/INT(J21/(Z21/100)),2))) | AJ21: 2 | AK21: =ROUND(IF(AJ21=2,0,((Z21*2)+(AA21*2))*CONFECCION!$B$35/100),2) | AM21: 2 | AQ21: =IF(S21=0,"",S21) | AR21: =IF(A21=0,"",VLOOKUP(L21,ARTICULOS!$A$10:$B$19,2)) | AS21: =IF(A21=0,"",T21&" * "&U21)&IF(AM21=1," PR","") | AT21: =IF(A21=0,"",VLOOKUP(E21,ARTICULOS!$D$10:$F$699,3)) | AU21: =IF(A21=0,"","c/ "&D21&" "&VLOOKUP(H21,COLORES!$A$7:$G$4394,7)) | AV21: =IF(A21=0,"",IF(V21=1,"Dobl. Sencillo","Dobl. "&V21&" cm.")) | AW21: =+IF(Y21=1,"SI","") | AX21: =IF(A21=0,"",IF(AB21=2,Z21&" * "&AA21,IF(Z21=AA21,"Redondo "&Z21&" * "&AA21,"Ovalado "&Z21&" * "&AA21))) | AY21: =IF(A21=0,"",AG21+AI21+AK21) | AZ21: =IF(A21=0,"",A21) | BA21: =IF(A21=0,"",ROUND(AY21*AZ21,2))
... A32: 0 | B32: 1 | D32: 1 | E32: =MATCH(C32,ARTICULOS!$F$10:$F$699,0) | F32: =+VLOOKUP(E32,ARTICULOS!$D$10:$I$699,6) | G32: =+F32&D32 | H32: =+MATCH(G32,COLORES!$E$7:$E$4394,0) | I32: =VLOOKUP(H32,COLORES!$A$7:$I$4394,8) | J32: =VLOOKUP(H32,COLORES!$A$7:$I$4394,9) | K32: =I32*(1+B32) | L32: 0 | M32: 0 | N32: 0 | O32: 0 | P32: 0 | Q32: 0 | S32: =IF(P32>0,IF(O32>0,"(/)"&O32&"*"&P32&IF(Q32>0,"+"&Q32,IF(Q32=0,"",Q32)),+M32&"*"&N32&"*"&P32&IF(Q32>0,"+"&Q32,IF(Q32=0,"",Q32))),"") | T32: =+IF(O32>0,O32+R32*2,M32+R32*2)+P32*2+Q32*2 | U32: =+IF(O32>0,O32+R32*2,N32+R32*2)+P32*2+Q32*2 | W32: =IF(V32=1,T32+5,T32+(V32*4)) | X32: =IF(V32=1,U32+5,U32+(V32*4)) | Y32: 0 | Z32: =IF(Y32=1,ROUNDUP(W32*(1+VLOOKUP(E32,ARTICULOS!$D$10:$H$699,5)),0),W32) | AA32: =IF(Y32=1,ROUNDUP(X32*(1+VLOOKUP(E32,ARTICULOS!$D$10:$H$699,4)),0),X32) | AB32: 2 | AD32: =IF(AC32=1,J32*100&Z32,"") | AE32: =IF(AC32=1,VLOOKUP(AD32,EMPALME!$C$2:$F$33,4),"") | AG32: =IF(L32=3,IF(V32=1,CONFECCION!$C$18,CONFECCION!$C$18*2),IF(V32=1,HLOOKUP(AA32,CONFECCION!$C$17:$AD$33,VLOOKUP(Z32,CONFECCION!$A$18:$B$33,2)-16),2*HLOOKUP(AA32,CONFECCION!$C$17:$AD$33,VLOOKUP(Z32,CONFECCION!$A$18:$B$33,2)-16)))*IF(AC32=1,3,1) | AI32: =IF(AC32=1,AA32/100*K32+IF(AF32>0,K32*(VLOOKUP(AD32,EMPALME!$C$2:$D$33,2)/100)/AF32,K32*(VLOOKUP(AD32,EMPALME!$C$2:$D$33,2)/100)/VLOOKUP(AD32,EMPALME!$C$2:$F$33,4)),IF(AH32=2,ROUND((K32*(AA32/100)-(I32/10)*INT((AA32/100)/0.55)*INT((J32-(Z32/100)*INT(J32/(Z32/100)))/0.55))/INT(J32/(Z32/100)),2),ROUND(K32*(AA32/100)/INT(J32/(Z32/100)),2))) | AJ32: 2 | AK32: =ROUND(IF(AJ32=2,0,((Z32*2)+(AA32*2))*CONFECCION!$B$35/100),2) | AM32: 2 | AQ32: =IF(S32=0,"",S32) | AR32: =IF(A32=0,"",VLOOKUP(L32,ARTICULOS!$A$10:$B$19,2)) | AS32: =IF(A32=0,"",T32&" * "&U32)&IF(AM32=1," PR","") | AT32: =IF(A32=0,"",VLOOKUP(E32,ARTICULOS!$D$10:$F$699,3)) | AU32: =IF(A32=0,"","c/ "&D32&" "&VLOOKUP(H32,COLORES!$A$7:$G$4394,7)) | AV32: =IF(A32=0,"",IF(V32=1,"Dobl. Sencillo","Dobl. "&V32&" cm.")) | AW32: =+IF(Y32=1,"SI","") | AX32: =IF(A32=0,"",IF(AB32=2,Z32&" * "&AA32,IF(Z32=AA32,"Redondo "&Z32&" * "&AA32,"Ovalado "&Z32&" * "&AA32))) | AY32: =IF(A32=0,"",AG32+AI32+AK32) | AZ32: =IF(A32=0,"",A32) | BA32: =IF(A32=0,"",ROUND(AY32*AZ32,2))
A33: 0 | B33: 1 | D33: 1 | E33: =MATCH(C33,ARTICULOS!$F$10:$F$699,0) | F33: =+VLOOKUP(E33,ARTICULOS!$D$10:$I$699,6) | G33: =+F33&D33 | H33: =+MATCH(G33,COLORES!$E$7:$E$4394,0) | I33: =VLOOKUP(H33,COLORES!$A$7:$I$4394,8) | J33: =VLOOKUP(H33,COLORES!$A$7:$I$4394,9) | K33: =I33*(1+B33) | L33: 0 | M33: 0 | N33: 0 | O33: 0 | P33: 0 | Q33: 0 | S33: =IF(P33>0,IF(O33>0,"(/)"&O33&"*"&P33&IF(Q33>0,"+"&Q33,IF(Q33=0,"",Q33)),+M33&"*"&N33&"*"&P33&IF(Q33>0,"+"&Q33,IF(Q33=0,"",Q33))),"") | T33: =+IF(O33>0,O33+R33*2,M33+R33*2)+P33*2+Q33*2 | U33: =+IF(O33>0,O33+R33*2,N33+R33*2)+P33*2+Q33*2 | W33: =IF(V33=1,T33+5,T33+(V33*4)) | X33: =IF(V33=1,U33+5,U33+(V33*4)) | Y33: 0 | Z33: =IF(Y33=1,ROUNDUP(W33*(1+VLOOKUP(E33,ARTICULOS!$D$10:$H$699,5)),0),W33) | AA33: =IF(Y33=1,ROUNDUP(X33*(1+VLOOKUP(E33,ARTICULOS!$D$10:$H$699,4)),0),X33) | AB33: 2 | AD33: =IF(AC33=1,J33*100&Z33,"") | AE33: =IF(AC33=1,VLOOKUP(AD33,EMPALME!$C$2:$F$33,4),"") | AG33: =IF(L33=3,IF(V33=1,CONFECCION!$C$18,CONFECCION!$C$18*2),IF(V33=1,HLOOKUP(AA33,CONFECCION!$C$17:$AD$33,VLOOKUP(Z33,CONFECCION!$A$18:$B$33,2)-16),2*HLOOKUP(AA33,CONFECCION!$C$17:$AD$33,VLOOKUP(Z33,CONFECCION!$A$18:$B$33,2)-16)))*IF(AC33=1,3,1) | AI33: =IF(AC33=1,AA33/100*K33+IF(AF33>0,K33*(VLOOKUP(AD33,EMPALME!$C$2:$D$33,2)/100)/AF33,K33*(VLOOKUP(AD33,EMPALME!$C$2:$D$33,2)/100)/VLOOKUP(AD33,EMPALME!$C$2:$F$33,4)),IF(AH33=2,ROUND((K33*(AA33/100)-(I33/10)*INT((AA33/100)/0.55)*INT((J33-(Z33/100)*INT(J33/(Z33/100)))/0.55))/INT(J33/(Z33/100)),2),ROUND(K33*(AA33/100)/INT(J33/(Z33/100)),2))) | AJ33: 2 | AK33: =ROUND(IF(AJ33=2,0,((Z33*2)+(AA33*2))*CONFECCION!$B$35/100),2) | AM33: 2 | AP33: Todas las prendas, seran identificadas con etiquerta color, según medida. | AQ33: =IF(S33=0,"",S33) | AR33: =IF(A33=0,"",VLOOKUP(L33,ARTICULOS!$A$10:$B$19,2)) | AS33: =IF(A33=0,"",T33&" * "&U33)&IF(AM33=1," PR","") | AT33: =IF(A33=0,"",VLOOKUP(E33,ARTICULOS!$D$10:$F$699,3)) | AU33: =IF(A33=0,"","c/ "&D33&" "&VLOOKUP(H33,COLORES!$A$7:$G$4394,7)) | AV33: =IF(A33=0,"",IF(V33=1,"Dobl. Sencillo","Dobl. "&V33&" cm.")) | AW33: =+IF(Y33=1,"SI","") | AX33: =IF(A33=0,"",IF(AB33=2,Z33&" * "&AA33,IF(Z33=AA33,"Redondo "&Z33&" * "&AA33,"Ovalado "&Z33&" * "&AA33))) | AY33: =IF(A33=0,"",AG33+AI33+AK33) | AZ33: =IF(A33=0,"",A33) | BA33: =IF(A33=0,"",ROUND(AY33*AZ33,2))
A34: 0 | B34: 1 | D34: 1 | E34: =MATCH(C34,ARTICULOS!$F$10:$F$699,0) | F34: =+VLOOKUP(E34,ARTICULOS!$D$10:$I$699,6) | G34: =+F34&D34 | H34: =+MATCH(G34,COLORES!$E$7:$E$4394,0) | I34: =VLOOKUP(H34,COLORES!$A$7:$I$4394,8) | J34: =VLOOKUP(H34,COLORES!$A$7:$I$4394,9) | K34: =I34*(1+B34) | L34: 0 | M34: 0 | N34: 0 | O34: 0 | P34: 0 | Q34: 0 | S34: =IF(P34>0,IF(O34>0,"(/)"&O34&"*"&P34&IF(Q34>0,"+"&Q34,IF(Q34=0,"",Q34)),+M34&"*"&N34&"*"&P34&IF(Q34>0,"+"&Q34,IF(Q34=0,"",Q34))),"") | T34: =+IF(O34>0,O34+R34*2,M34+R34*2)+P34*2+Q34*2 | U34: =+IF(O34>0,O34+R34*2,N34+R34*2)+P34*2+Q34*2 | W34: =IF(V34=1,T34+5,T34+(V34*4)) | X34: =IF(V34=1,U34+5,U34+(V34*4)) | Y34: 0 | Z34: =IF(Y34=1,ROUNDUP(W34*(1+VLOOKUP(E34,ARTICULOS!$D$10:$H$699,5)),0),W34) | AA34: =IF(Y34=1,ROUNDUP(X34*(1+VLOOKUP(E34,ARTICULOS!$D$10:$H$699,4)),0),X34) | AB34: 2 | AD34: =IF(AC34=1,J34*100&Z34,"") | AE34: =IF(AC34=1,VLOOKUP(AD34,EMPALME!$C$2:$F$33,4),"") | AG34: =IF(L34=3,IF(V34=1,CONFECCION!$C$18,CONFECCION!$C$18*2),IF(V34=1,HLOOKUP(AA34,CONFECCION!$C$17:$AD$33,VLOOKUP(Z34,CONFECCION!$A$18:$B$33,2)-16),2*HLOOKUP(AA34,CONFECCION!$C$17:$AD$33,VLOOKUP(Z34,CONFECCION!$A$18:$B$33,2)-16)))*IF(AC34=1,3,1) | AI34: =IF(AC34=1,AA34/100*K34+IF(AF34>0,K34*(VLOOKUP(AD34,EMPALME!$C$2:$D$33,2)/100)/AF34,K34*(VLOOKUP(AD34,EMPALME!$C$2:$D$33,2)/100)/VLOOKUP(AD34,EMPALME!$C$2:$F$33,4)),IF(AH34=2,ROUND((K34*(AA34/100)-(I34/10)*INT((AA34/100)/0.55)*INT((J34-(Z34/100)*INT(J34/(Z34/100)))/0.55))/INT(J34/(Z34/100)),2),ROUND(K34*(AA34/100)/INT(J34/(Z34/100)),2))) | AJ34: 2 | AK34: =ROUND(IF(AJ34=2,0,((Z34*2)+(AA34*2))*CONFECCION!$B$35/100),2) | AM34: 2 | AP34: Estos precios no incluyen I.V.A. | AQ34: =IF(S34=0,"",S34) | AR34: =IF(A34=0,"",VLOOKUP(L34,ARTICULOS!$A$10:$B$19,2)) | AS34: =IF(A34=0,"",T34&" * "&U34)&IF(AM34=1," PR","") | AT34: =IF(A34=0,"",VLOOKUP(E34,ARTICULOS!$D$10:$F$699,3)) | AU34: =IF(A34=0,"","c/ "&D34&" "&VLOOKUP(H34,COLORES!$A$7:$G$4394,7)) | AV34: =IF(A34=0,"",IF(V34=1,"Dobl. Sencillo","Dobl. "&V34&" cm.")) | AW34: =+IF(Y34=1,"SI","") | AX34: =IF(A34=0,"",IF(AB34=2,Z34&" * "&AA34,IF(Z34=AA34,"Redondo "&Z34&" * "&AA34,"Ovalado "&Z34&" * "&AA34))) | AY34: =IF(A34=0,"",AG34+AI34+AK34) | AZ34: =IF(A34=0,"",A34) | BA34: =IF(A34=0,"",ROUND(AY34*AZ34,2))
A35: 0 | B35: 1 | D35: 1 | E35: =MATCH(C35,ARTICULOS!$F$10:$F$699,0) | F35: =+VLOOKUP(E35,ARTICULOS!$D$10:$I$699,6) | G35: =+F35&D35 | H35: =+MATCH(G35,COLORES!$E$7:$E$4394,0) | I35: =VLOOKUP(H35,COLORES!$A$7:$I$4394,8) | J35: =VLOOKUP(H35,COLORES!$A$7:$I$4394,9) | K35: =I35*(1+B35) | L35: 0 | M35: 0 | N35: 0 | O35: 0 | P35: 0 | Q35: 0 | S35: =IF(P35>0,IF(O35>0,"(/)"&O35&"*"&P35&IF(Q35>0,"+"&Q35,IF(Q35=0,"",Q35)),+M35&"*"&N35&"*"&P35&IF(Q35>0,"+"&Q35,IF(Q35=0,"",Q35))),"") | T35: =+IF(O35>0,O35+R35*2,M35+R35*2)+P35*2+Q35*2 | U35: =+IF(O35>0,O35+R35*2,N35+R35*2)+P35*2+Q35*2 | W35: =IF(V35=1,T35+5,T35+(V35*4)) | X35: =IF(V35=1,U35+5,U35+(V35*4)) | Y35: 0 | Z35: =IF(Y35=1,ROUNDUP(W35*(1+VLOOKUP(E35,ARTICULOS!$D$10:$H$699,5)),0),W35) | AA35: =IF(Y35=1,ROUNDUP(X35*(1+VLOOKUP(E35,ARTICULOS!$D$10:$H$699,4)),0),X35) | AB35: 2 | AD35: =IF(AC35=1,J35*100&Z35,"") | AE35: =IF(AC35=1,VLOOKUP(AD35,EMPALME!$C$2:$F$33,4),"") | AG35: =IF(L35=3,IF(V35=1,CONFECCION!$C$18,CONFECCION!$C$18*2),IF(V35=1,HLOOKUP(AA35,CONFECCION!$C$17:$AD$33,VLOOKUP(Z35,CONFECCION!$A$18:$B$33,2)-16),2*HLOOKUP(AA35,CONFECCION!$C$17:$AD$33,VLOOKUP(Z35,CONFECCION!$A$18:$B$33,2)-16)))*IF(AC35=1,3,1) | AI35: =IF(AC35=1,AA35/100*K35+IF(AF35>0,K35*(VLOOKUP(AD35,EMPALME!$C$2:$D$33,2)/100)/AF35,K35*(VLOOKUP(AD35,EMPALME!$C$2:$D$33,2)/100)/VLOOKUP(AD35,EMPALME!$C$2:$F$33,4)),IF(AH35=2,ROUND((K35*(AA35/100)-(I35/10)*INT((AA35/100)/0.55)*INT((J35-(Z35/100)*INT(J35/(Z35/100)))/0.55))/INT(J35/(Z35/100)),2),ROUND(K35*(AA35/100)/INT(J35/(Z35/100)),2))) | AJ35: 2 | AK35: =ROUND(IF(AJ35=2,0,((Z35*2)+(AA35*2))*CONFECCION!$B$35/100),2) | AM35: 2 | AP35: Considerado encogimiento. | AQ35: =IF(S35=0,"",S35) | AR35: =IF(A35=0,"",VLOOKUP(L35,ARTICULOS!$A$10:$B$19,2)) | AS35: =IF(A35=0,"",T35&" * "&U35)&IF(AM35=1," PR","") | AT35: =IF(A35=0,"",VLOOKUP(E35,ARTICULOS!$D$10:$F$699,3)) | AU35: =IF(A35=0,"","c/ "&D35&" "&VLOOKUP(H35,COLORES!$A$7:$G$4394,7)) | AV35: =IF(A35=0,"",IF(V35=1,"Dobl. Sencillo","Dobl. "&V35&" cm.")) | AW35: =+IF(Y35=1,"SI","") | AX35: =IF(A35=0,"",IF(AB35=2,Z35&" * "&AA35,IF(Z35=AA35,"Redondo "&Z35&" * "&AA35,"Ovalado "&Z35&" * "&AA35))) | AY35: =IF(A35=0,"",AG35+AI35+AK35) | AZ35: =IF(A35=0,"",A35) | BA35: =IF(A35=0,"",ROUND(AY35*AZ35,2))
A36: 0 | B36: 1 | D36: 1 | E36: =MATCH(C36,ARTICULOS!$F$10:$F$699,0) | F36: =+VLOOKUP(E36,ARTICULOS!$D$10:$I$699,6) | G36: =+F36&D36 | H36: =+MATCH(G36,COLORES!$E$7:$E$4394,0) | I36: =VLOOKUP(H36,COLORES!$A$7:$I$4394,8) | J36: =VLOOKUP(H36,COLORES!$A$7:$I$4394,9) | K36: =I36*(1+B36) | L36: 0 | M36: 0 | N36: 0 | O36: 0 | P36: 0 | Q36: 0 | S36: =IF(P36>0,IF(O36>0,"(/)"&O36&"*"&P36&IF(Q36>0,"+"&Q36,IF(Q36=0,"",Q36)),+M36&"*"&N36&"*"&P36&IF(Q36>0,"+"&Q36,IF(Q36=0,"",Q36))),"") | T36: =+IF(O36>0,O36+R36*2,M36+R36*2)+P36*2+Q36*2 | U36: =+IF(O36>0,O36+R36*2,N36+R36*2)+P36*2+Q36*2 | W36: =IF(V36=1,T36+5,T36+(V36*4)) | X36: =IF(V36=1,U36+5,U36+(V36*4)) | Y36: 0 | Z36: =IF(Y36=1,ROUNDUP(W36*(1+VLOOKUP(E36,ARTICULOS!$D$10:$H$699,5)),0),W36) | AA36: =IF(Y36=1,ROUNDUP(X36*(1+VLOOKUP(E36,ARTICULOS!$D$10:$H$699,4)),0),X36) | AB36: 2 | AD36: =IF(AC36=1,J36*100&Z36,"") | AE36: =IF(AC36=1,VLOOKUP(AD36,EMPALME!$C$2:$F$33,4),"") | AG36: =IF(L36=3,IF(V36=1,CONFECCION!$C$18,CONFECCION!$C$18*2),IF(V36=1,HLOOKUP(AA36,CONFECCION!$C$17:$AD$33,VLOOKUP(Z36,CONFECCION!$A$18:$B$33,2)-16),2*HLOOKUP(AA36,CONFECCION!$C$17:$AD$33,VLOOKUP(Z36,CONFECCION!$A$18:$B$33,2)-16)))*IF(AC36=1,3,1) | AI36: =IF(AC36=1,AA36/100*K36+IF(AF36>0,K36*(VLOOKUP(AD36,EMPALME!$C$2:$D$33,2)/100)/AF36,K36*(VLOOKUP(AD36,EMPALME!$C$2:$D$33,2)/100)/VLOOKUP(AD36,EMPALME!$C$2:$F$33,4)),IF(AH36=2,ROUND((K36*(AA36/100)-(I36/10)*INT((AA36/100)/0.55)*INT((J36-(Z36/100)*INT(J36/(Z36/100)))/0.55))/INT(J36/(Z36/100)),2),ROUND(K36*(AA36/100)/INT(J36/(Z36/100)),2))) | AJ36: 2 | AK36: =ROUND(IF(AJ36=2,0,((Z36*2)+(AA36*2))*CONFECCION!$B$35/100),2) | AM36: 2 | AP36: Confección a Capet | AQ36: =IF(S36=0,"",S36) | AR36: =IF(A36=0,"",VLOOKUP(L36,ARTICULOS!$A$10:$B$19,2)) | AS36: =IF(A36=0,"",T36&" * "&U36)&IF(AM36=1," PR","") | AT36: =IF(A36=0,"",VLOOKUP(E36,ARTICULOS!$D$10:$F$699,3)) | AU36: =IF(A36=0,"","c/ "&D36&" "&VLOOKUP(H36,COLORES!$A$7:$G$4394,7)) | AV36: =IF(A36=0,"",IF(V36=1,"Dobl. Sencillo","Dobl. "&V36&" cm.")) | AW36: =+IF(Y36=1,"SI","") | AX36: =IF(A36=0,"",IF(AB36=2,Z36&" * "&AA36,IF(Z36=AA36,"Redondo "&Z36&" * "&AA36,"Ovalado "&Z36&" * "&AA36))) | AY36: =IF(A36=0,"",AG36+AI36+AK36) | AZ36: =IF(A36=0,"",A36) | BA36: =IF(A36=0,"",ROUND(AY36*AZ36,2))
A37: 0 | B37: 1 | D37: 1 | E37: =MATCH(C37,ARTICULOS!$F$10:$F$699,0) | F37: =+VLOOKUP(E37,ARTICULOS!$D$10:$I$699,6) | G37: =+F37&D37 | H37: =+MATCH(G37,COLORES!$E$7:$E$4394,0) | I37: =VLOOKUP(H37,COLORES!$A$7:$I$4394,8) | J37: =VLOOKUP(H37,COLORES!$A$7:$I$4394,9) | K37: =I37*(1+B37) | L37: 0 | M37: 0 | N37: 0 | O37: 0 | P37: 0 | Q37: 0 | S37: =IF(P37>0,IF(O37>0,"(/)"&O37&"*"&P37&IF(Q37>0,"+"&Q37,IF(Q37=0,"",Q37)),+M37&"*"&N37&"*"&P37&IF(Q37>0,"+"&Q37,IF(Q37=0,"",Q37))),"") | T37: =+IF(O37>0,O37+R37*2,M37+R37*2)+P37*2+Q37*2 | U37: =+IF(O37>0,O37+R37*2,N37+R37*2)+P37*2+Q37*2 | W37: =IF(V37=1,T37+5,T37+(V37*4)) | X37: =IF(V37=1,U37+5,U37+(V37*4)) | Y37: 0 | Z37: =IF(Y37=1,ROUNDUP(W37*(1+VLOOKUP(E37,ARTICULOS!$D$10:$H$699,5)),0),W37) | AA37: =IF(Y37=1,ROUNDUP(X37*(1+VLOOKUP(E37,ARTICULOS!$D$10:$H$699,4)),0),X37) | AB37: 2 | AD37: =IF(AC37=1,J37*100&Z37,"") | AE37: =IF(AC37=1,VLOOKUP(AD37,EMPALME!$C$2:$F$33,4),"") | AG37: =IF(L37=3,IF(V37=1,CONFECCION!$C$18,CONFECCION!$C$18*2),IF(V37=1,HLOOKUP(AA37,CONFECCION!$C$17:$AD$33,VLOOKUP(Z37,CONFECCION!$A$18:$B$33,2)-16),2*HLOOKUP(AA37,CONFECCION!$C$17:$AD$33,VLOOKUP(Z37,CONFECCION!$A$18:$B$33,2)-16)))*IF(AC37=1,3,1) | AI37: =IF(AC37=1,AA37/100*K37+IF(AF37>0,K37*(VLOOKUP(AD37,EMPALME!$C$2:$D$33,2)/100)/AF37,K37*(VLOOKUP(AD37,EMPALME!$C$2:$D$33,2)/100)/VLOOKUP(AD37,EMPALME!$C$2:$F$33,4)),IF(AH37=2,ROUND((K37*(AA37/100)-(I37/10)*INT((AA37/100)/0.55)*INT((J37-(Z37/100)*INT(J37/(Z37/100)))/0.55))/INT(J37/(Z37/100)),2),ROUND(K37*(AA37/100)/INT(J37/(Z37/100)),2))) | AJ37: 2 | AK37: =ROUND(IF(AJ37=2,0,((Z37*2)+(AA37*2))*CONFECCION!$B$35/100),2) | AM37: 2 | AP37: F. Pago : 50% a la aceptacion de presupuesto. | AQ37: =IF(S37=0,"",S37) | AR37: =IF(A37=0,"",VLOOKUP(L37,ARTICULOS!$A$10:$B$19,2)) | AS37: =IF(A37=0,"",T37&" * "&U37)&IF(AM37=1," PR","") | AT37: =IF(A37=0,"",VLOOKUP(E37,ARTICULOS!$D$10:$F$699,3)) | AU37: =IF(A37=0,"","c/ "&D37&" "&VLOOKUP(H37,COLORES!$A$7:$G$4394,7)) | AV37: =IF(A37=0,"",IF(V37=1,"Dobl. Sencillo","Dobl. "&V37&" cm.")) | AW37: =+IF(Y37=1,"SI","") | AX37: =IF(A37=0,"",IF(AB37=2,Z37&" * "&AA37,IF(Z37=AA37,"Redondo "&Z37&" * "&AA37,"Ovalado "&Z37&" * "&AA37))) | AY37: =IF(A37=0,"",AG37+AI37+AK37) | AZ37: =IF(A37=0,"",A37) | BA37: =IF(A37=0,"",ROUND(AY37*AZ37,2))
A38: 0 | B38: 1 | D38: 1 | E38: =MATCH(C38,ARTICULOS!$F$10:$F$699,0) | F38: =+VLOOKUP(E38,ARTICULOS!$D$10:$I$699,6) | G38: =+F38&D38 | H38: =+MATCH(G38,COLORES!$E$7:$E$4394,0) | I38: =VLOOKUP(H38,COLORES!$A$7:$I$4394,8) | J38: =VLOOKUP(H38,COLORES!$A$7:$I$4394,9) | K38: =I38*(1+B38) | L38: 0 | M38: 0 | N38: 0 | O38: 0 | P38: 0 | Q38: 0 | S38: =IF(P38>0,IF(O38>0,"(/)"&O38&"*"&P38&IF(Q38>0,"+"&Q38,IF(Q38=0,"",Q38)),+M38&"*"&N38&"*"&P38&IF(Q38>0,"+"&Q38,IF(Q38=0,"",Q38))),"") | T38: =+IF(O38>0,O38+R38*2,M38+R38*2)+P38*2+Q38*2 | U38: =+IF(O38>0,O38+R38*2,N38+R38*2)+P38*2+Q38*2 | W38: =IF(V38=1,T38+5,T38+(V38*4)) | X38: =IF(V38=1,U38+5,U38+(V38*4)) | Y38: 0 | Z38: =IF(Y38=1,ROUNDUP(W38*(1+VLOOKUP(E38,ARTICULOS!$D$10:$H$699,5)),0),W38) | AA38: =IF(Y38=1,ROUNDUP(X38*(1+VLOOKUP(E38,ARTICULOS!$D$10:$H$699,4)),0),X38) | AB38: 2 | AD38: =IF(AC38=1,J38*100&Z38,"") | AE38: =IF(AC38=1,VLOOKUP(AD38,EMPALME!$C$2:$F$33,4),"") | AG38: =IF(L38=3,IF(V38=1,CONFECCION!$C$18,CONFECCION!$C$18*2),IF(V38=1,HLOOKUP(AA38,CONFECCION!$C$17:$AD$33,VLOOKUP(Z38,CONFECCION!$A$18:$B$33,2)-16),2*HLOOKUP(AA38,CONFECCION!$C$17:$AD$33,VLOOKUP(Z38,CONFECCION!$A$18:$B$33,2)-16)))*IF(AC38=1,3,1) | AI38: =IF(AC38=1,AA38/100*K38+IF(AF38>0,K38*(VLOOKUP(AD38,EMPALME!$C$2:$D$33,2)/100)/AF38,K38*(VLOOKUP(AD38,EMPALME!$C$2:$D$33,2)/100)/VLOOKUP(AD38,EMPALME!$C$2:$F$33,4)),IF(AH38=2,ROUND((K38*(AA38/100)-(I38/10)*INT((AA38/100)/0.55)*INT((J38-(Z38/100)*INT(J38/(Z38/100)))/0.55))/INT(J38/(Z38/100)),2),ROUND(K38*(AA38/100)/INT(J38/(Z38/100)),2))) | AJ38: 2 | AK38: =ROUND(IF(AJ38=2,0,((Z38*2)+(AA38*2))*CONFECCION!$B$35/100),2) | AM38: 2 | AP38: Resto a la entrega de mercancia | AQ38: =IF(S38=0,"",S38) | AR38: =IF(A38=0,"",VLOOKUP(L38,ARTICULOS!$A$10:$B$19,2)) | AS38: =IF(A38=0,"",T38&" * "&U38)&IF(AM38=1," PR","") | AT38: =IF(A38=0,"",VLOOKUP(E38,ARTICULOS!$D$10:$F$699,3)) | AU38: =IF(A38=0,"","c/ "&D38&" "&VLOOKUP(H38,COLORES!$A$7:$G$4394,7)) | AV38: =IF(A38=0,"",IF(V38=1,"Dobl. Sencillo","Dobl. "&V38&" cm.")) | AW38: =+IF(Y38=1,"SI","") | AX38: =IF(A38=0,"",IF(AB38=2,Z38&" * "&AA38,IF(Z38=AA38,"Redondo "&Z38&" * "&AA38,"Ovalado "&Z38&" * "&AA38))) | AY38: =IF(A38=0,"",AG38+AI38+AK38) | AZ38: =IF(A38=0,"",A38) | BA38: =IF(A38=0,"",ROUND(AY38*AZ38,2))
A39: 0 | B39: 1 | D39: 1 | E39: =MATCH(C39,ARTICULOS!$F$10:$F$699,0) | F39: =+VLOOKUP(E39,ARTICULOS!$D$10:$I$699,6) | G39: =+F39&D39 | H39: =+MATCH(G39,COLORES!$E$7:$E$4394,0) | I39: =VLOOKUP(H39,COLORES!$A$7:$I$4394,8) | J39: =VLOOKUP(H39,COLORES!$A$7:$I$4394,9) | K39: =I39*(1+B39) | L39: 0 | M39: 0 | N39: 0 | O39: 0 | P39: 0 | Q39: 0 | S39: =IF(P39>0,IF(O39>0,"(/)"&O39&"*"&P39&IF(Q39>0,"+"&Q39,IF(Q39=0,"",Q39)),+M39&"*"&N39&"*"&P39&IF(Q39>0,"+"&Q39,IF(Q39=0,"",Q39))),"") | T39: =+IF(O39>0,O39+R39*2,M39+R39*2)+P39*2+Q39*2 | U39: =+IF(O39>0,O39+R39*2,N39+R39*2)+P39*2+Q39*2 | W39: =IF(V39=1,T39+5,T39+(V39*4)) | X39: =IF(V39=1,U39+5,U39+(V39*4)) | Y39: 0 | Z39: =IF(Y39=1,ROUNDUP(W39*(1+VLOOKUP(E39,ARTICULOS!$D$10:$H$699,5)),0),W39) | AA39: =IF(Y39=1,ROUNDUP(X39*(1+VLOOKUP(E39,ARTICULOS!$D$10:$H$699,4)),0),X39) | AB39: 2 | AD39: =IF(AC39=1,J39*100&Z39,"") | AE39: =IF(AC39=1,VLOOKUP(AD39,EMPALME!$C$2:$F$33,4),"") | AG39: =IF(L39=3,IF(V39=1,CONFECCION!$C$18,CONFECCION!$C$18*2),IF(V39=1,HLOOKUP(AA39,CONFECCION!$C$17:$AD$33,VLOOKUP(Z39,CONFECCION!$A$18:$B$33,2)-16),2*HLOOKUP(AA39,CONFECCION!$C$17:$AD$33,VLOOKUP(Z39,CONFECCION!$A$18:$B$33,2)-16)))*IF(AC39=1,3,1) | AI39: =IF(AC39=1,AA39/100*K39+IF(AF39>0,K39*(VLOOKUP(AD39,EMPALME!$C$2:$D$33,2)/100)/AF39,K39*(VLOOKUP(AD39,EMPALME!$C$2:$D$33,2)/100)/VLOOKUP(AD39,EMPALME!$C$2:$F$33,4)),IF(AH39=2,ROUND((K39*(AA39/100)-(I39/10)*INT((AA39/100)/0.55)*INT((J39-(Z39/100)*INT(J39/(Z39/100)))/0.55))/INT(J39/(Z39/100)),2),ROUND(K39*(AA39/100)/INT(J39/(Z39/100)),2))) | AJ39: 2 | AK39: =ROUND(IF(AJ39=2,0,((Z39*2)+(AA39*2))*CONFECCION!$B$35/100),2) | AM39: 2 | AP39: La cantidad de prendas, puede variar en un + - 10% | AQ39: =IF(S39=0,"",S39) | AR39: =IF(A39=0,"",VLOOKUP(L39,ARTICULOS!$A$10:$B$19,2)) | AS39: =IF(A39=0,"",T39&" * "&U39)&IF(AM39=1," PR","") | AT39: =IF(A39=0,"",VLOOKUP(E39,ARTICULOS!$D$10:$F$699,3)) | AU39: =IF(A39=0,"","c/ "&D39&" "&VLOOKUP(H39,COLORES!$A$7:$G$4394,7)) | AV39: =IF(A39=0,"",IF(V39=1,"Dobl. Sencillo","Dobl. "&V39&" cm.")) | AW39: =+IF(Y39=1,"SI","") | AX39: =IF(A39=0,"",IF(AB39=2,Z39&" * "&AA39,IF(Z39=AA39,"Redondo "&Z39&" * "&AA39,"Ovalado "&Z39&" * "&AA39))) | AY39: =IF(A39=0,"",AG39+AI39+AK39) | AZ39: =IF(A39=0,"",A39) | BA39: =IF(A39=0,"",ROUND(AY39*AZ39,2))
A40: 0 | B40: 1 | D40: 1 | E40: =MATCH(C40,ARTICULOS!$F$10:$F$699,0) | F40: =+VLOOKUP(E40,ARTICULOS!$D$10:$I$699,6) | G40: =+F40&D40 | H40: =+MATCH(G40,COLORES!$E$7:$E$4394,0) | I40: =VLOOKUP(H40,COLORES!$A$7:$I$4394,8) | J40: =VLOOKUP(H40,COLORES!$A$7:$I$4394,9) | K40: =I40*(1+B40) | L40: 0 | M40: 0 | N40: 0 | O40: 0 | P40: 0 | Q40: 0 | S40: =IF(P40>0,IF(O40>0,"(/)"&O40&"*"&P40&IF(Q40>0,"+"&Q40,IF(Q40=0,"",Q40)),+M40&"*"&N40&"*"&P40&IF(Q40>0,"+"&Q40,IF(Q40=0,"",Q40))),"") | T40: =+IF(O40>0,O40+R40*2,M40+R40*2)+P40*2+Q40*2 | U40: =+IF(O40>0,O40+R40*2,N40+R40*2)+P40*2+Q40*2 | W40: =IF(V40=1,T40+5,T40+(V40*4)) | X40: =IF(V40=1,U40+5,U40+(V40*4)) | Y40: 0 | Z40: =IF(Y40=1,ROUNDUP(W40*(1+VLOOKUP(E40,ARTICULOS!$D$10:$H$699,5)),0),W40) | AA40: =IF(Y40=1,ROUNDUP(X40*(1+VLOOKUP(E40,ARTICULOS!$D$10:$H$699,4)),0),X40) | AB40: 2 | AD40: =IF(AC40=1,J40*100&Z40,"") | AE40: =IF(AC40=1,VLOOKUP(AD40,EMPALME!$C$2:$F$33,4),"") | AG40: =IF(L40=3,IF(V40=1,CONFECCION!$C$18,CONFECCION!$C$18*2),IF(V40=1,HLOOKUP(AA40,CONFECCION!$C$17:$AD$33,VLOOKUP(Z40,CONFECCION!$A$18:$B$33,2)-16),2*HLOOKUP(AA40,CONFECCION!$C$17:$AD$33,VLOOKUP(Z40,CONFECCION!$A$18:$B$33,2)-16)))*IF(AC40=1,3,1) | AI40: =IF(AC40=1,AA40/100*K40+IF(AF40>0,K40*(VLOOKUP(AD40,EMPALME!$C$2:$D$33,2)/100)/AF40,K40*(VLOOKUP(AD40,EMPALME!$C$2:$D$33,2)/100)/VLOOKUP(AD40,EMPALME!$C$2:$F$33,4)),IF(AH40=2,ROUND((K40*(AA40/100)-(I40/10)*INT((AA40/100)/0.55)*INT((J40-(Z40/100)*INT(J40/(Z40/100)))/0.55))/INT(J40/(Z40/100)),2),ROUND(K40*(AA40/100)/INT(J40/(Z40/100)),2))) | AJ40: 2 | AK40: =ROUND(IF(AJ40=2,0,((Z40*2)+(AA40*2))*CONFECCION!$B$35/100),2) | AM40: 2 | AQ40: =IF(S40=0,"",S40) | AR40: =IF(A40=0,"",VLOOKUP(L40,ARTICULOS!$A$10:$B$19,2)) | AS40: =IF(A40=0,"",T40&" * "&U40)&IF(AM40=1," PR","") | AT40: =IF(A40=0,"",VLOOKUP(E40,ARTICULOS!$D$10:$F$699,3)) | AU40: =IF(A40=0,"","c/ "&D40&" "&VLOOKUP(H40,COLORES!$A$7:$G$4394,7)) | AV40: =IF(A40=0,"",IF(V40=1,"Dobl. Sencillo","Dobl. "&V40&" cm.")) | AW40: =+IF(Y40=1,"SI","") | AX40: =IF(A40=0,"",IF(AB40=2,Z40&" * "&AA40,IF(Z40=AA40,"Redondo "&Z40&" * "&AA40,"Ovalado "&Z40&" * "&AA40))) | AY40: =IF(A40=0,"",AG40+AI40+AK40) | AZ40: =IF(A40=0,"",A40) | BA40: =IF(A40=0,"",ROUND(AY40*AZ40,2))
A41: 0 | B41: 1 | D41: 1 | E41: =MATCH(C41,ARTICULOS!$F$10:$F$699,0) | F41: =+VLOOKUP(E41,ARTICULOS!$D$10:$I$699,6) | G41: =+F41&D41 | H41: =+MATCH(G41,COLORES!$E$7:$E$4394,0) | I41: =VLOOKUP(H41,COLORES!$A$7:$I$4394,8) | J41: =VLOOKUP(H41,COLORES!$A$7:$I$4394,9) | K41: =I41*(1+B41) | L41: 0 | M41: 0 | N41: 0 | O41: 0 | P41: 0 | Q41: 0 | S41: =IF(P41>0,IF(O41>0,"(/)"&O41&"*"&P41&IF(Q41>0,"+"&Q41,IF(Q41=0,"",Q41)),+M41&"*"&N41&"*"&P41&IF(Q41>0,"+"&Q41,IF(Q41=0,"",Q41))),"") | T41: =+IF(O41>0,O41+R41*2,M41+R41*2)+P41*2+Q41*2 | U41: =+IF(O41>0,O41+R41*2,N41+R41*2)+P41*2+Q41*2 | W41: =IF(V41=1,T41+5,T41+(V41*4)) | X41: =IF(V41=1,U41+5,U41+(V41*4)) | Y41: 0 | Z41: =IF(Y41=1,ROUNDUP(W41*(1+VLOOKUP(E41,ARTICULOS!$D$10:$H$699,5)),0),W41) | AA41: =IF(Y41=1,ROUNDUP(X41*(1+VLOOKUP(E41,ARTICULOS!$D$10:$H$699,4)),0),X41) | AB41: 2 | AD41: =IF(AC41=1,J41*100&Z41,"") | AE41: =IF(AC41=1,VLOOKUP(AD41,EMPALME!$C$2:$F$33,4),"") | AG41: =IF(L41=3,IF(V41=1,CONFECCION!$C$18,CONFECCION!$C$18*2),IF(V41=1,HLOOKUP(AA41,CONFECCION!$C$17:$AD$33,VLOOKUP(Z41,CONFECCION!$A$18:$B$33,2)-16),2*HLOOKUP(AA41,CONFECCION!$C$17:$AD$33,VLOOKUP(Z41,CONFECCION!$A$18:$B$33,2)-16)))*IF(AC41=1,3,1) | AI41: =IF(AC41=1,AA41/100*K41+IF(AF41>0,K41*(VLOOKUP(AD41,EMPALME!$C$2:$D$33,2)/100)/AF41,K41*(VLOOKUP(AD41,EMPALME!$C$2:$D$33,2)/100)/VLOOKUP(AD41,EMPALME!$C$2:$F$33,4)),IF(AH41=2,ROUND((K41*(AA41/100)-(I41/10)*INT((AA41/100)/0.55)*INT((J41-(Z41/100)*INT(J41/(Z41/100)))/0.55))/INT(J41/(Z41/100)),2),ROUND(K41*(AA41/100)/INT(J41/(Z41/100)),2))) | AJ41: 2 | AK41: =ROUND(IF(AJ41=2,0,((Z41*2)+(AA41*2))*CONFECCION!$B$35/100),2) | AM41: 2 | AQ41: =IF(S41=0,"",S41) | AR41: =IF(A41=0,"",VLOOKUP(L41,ARTICULOS!$A$10:$B$19,2)) | AS41: =IF(A41=0,"",T41&" * "&U41)&IF(AM41=1," PR","") | AT41: =IF(A41=0,"",VLOOKUP(E41,ARTICULOS!$D$10:$F$699,3)) | AU41: =IF(A41=0,"","c/ "&D41&" "&VLOOKUP(H41,COLORES!$A$7:$G$4394,7)) | AV41: =IF(A41=0,"",IF(V41=1,"Dobl. Sencillo","Dobl. "&V41&" cm.")) | AW41: =+IF(Y41=1,"SI","") | AX41: =IF(A41=0,"",IF(AB41=2,Z41&" * "&AA41,IF(Z41=AA41,"Redondo "&Z41&" * "&AA41,"Ovalado "&Z41&" * "&AA41))) | AY41: =IF(A41=0,"",AG41+AI41+AK41) | AZ41: =IF(A41=0,"",A41) | BA41: =IF(A41=0,"",ROUND(AY41*AZ41,2))
A42: 0 | B42: 1 | D42: 1 | E42: =MATCH(C42,ARTICULOS!$F$10:$F$699,0) | F42: =+VLOOKUP(E42,ARTICULOS!$D$10:$I$699,6) | G42: =+F42&D42 | H42: =+MATCH(G42,COLORES!$E$7:$E$4394,0) | I42: =VLOOKUP(H42,COLORES!$A$7:$I$4394,8) | J42: =VLOOKUP(H42,COLORES!$A$7:$I$4394,9) | K42: =I42*(1+B42) | L42: 0 | M42: 0 | N42: 0 | O42: 0 | P42: 0 | Q42: 0 | S42: =IF(P42>0,IF(O42>0,"(/)"&O42&"*"&P42&IF(Q42>0,"+"&Q42,IF(Q42=0,"",Q42)),+M42&"*"&N42&"*"&P42&IF(Q42>0,"+"&Q42,IF(Q42=0,"",Q42))),"") | T42: =+IF(O42>0,O42+R42*2,M42+R42*2)+P42*2+Q42*2 | U42: =+IF(O42>0,O42+R42*2,N42+R42*2)+P42*2+Q42*2 | W42: =IF(V42=1,T42+5,T42+(V42*4)) | X42: =IF(V42=1,U42+5,U42+(V42*4)) | Y42: 0 | Z42: =IF(Y42=1,ROUNDUP(W42*(1+VLOOKUP(E42,ARTICULOS!$D$10:$H$699,5)),0),W42) | AA42: =IF(Y42=1,ROUNDUP(X42*(1+VLOOKUP(E42,ARTICULOS!$D$10:$H$699,4)),0),X42) | AB42: 2 | AD42: =IF(AC42=1,J42*100&Z42,"") | AE42: =IF(AC42=1,VLOOKUP(AD42,EMPALME!$C$2:$F$33,4),"") | AG42: =IF(L42=3,IF(V42=1,CONFECCION!$C$18,CONFECCION!$C$18*2),IF(V42=1,HLOOKUP(AA42,CONFECCION!$C$17:$AD$33,VLOOKUP(Z42,CONFECCION!$A$18:$B$33,2)-16),2*HLOOKUP(AA42,CONFECCION!$C$17:$AD$33,VLOOKUP(Z42,CONFECCION!$A$18:$B$33,2)-16)))*IF(AC42=1,3,1) | AI42: =IF(AC42=1,AA42/100*K42+IF(AF42>0,K42*(VLOOKUP(AD42,EMPALME!$C$2:$D$33,2)/100)/AF42,K42*(VLOOKUP(AD42,EMPALME!$C$2:$D$33,2)/100)/VLOOKUP(AD42,EMPALME!$C$2:$F$33,4)),IF(AH42=2,ROUND((K42*(AA42/100)-(I42/10)*INT((AA42/100)/0.55)*INT((J42-(Z42/100)*INT(J42/(Z42/100)))/0.55))/INT(J42/(Z42/100)),2),ROUND(K42*(AA42/100)/INT(J42/(Z42/100)),2))) | AJ42: 2 | AK42: =ROUND(IF(AJ42=2,0,((Z42*2)+(AA42*2))*CONFECCION!$B$35/100),2) | AM42: 2 | AQ42: =IF(S42=0,"",S42) | AR42: =IF(A42=0,"",VLOOKUP(L42,ARTICULOS!$A$10:$B$19,2)) | AS42: =IF(A42=0,"",T42&" * "&U42)&IF(AM42=1," PR","") | AT42: =IF(A42=0,"",VLOOKUP(E42,ARTICULOS!$D$10:$F$699,3)) | AU42: =IF(A42=0,"","c/ "&D42&" "&VLOOKUP(H42,COLORES!$A$7:$G$4394,7)) | AV42: =IF(A42=0,"",IF(V42=1,"Dobl. Sencillo","Dobl. "&V42&" cm.")) | AW42: =+IF(Y42=1,"SI","") | AX42: =IF(A42=0,"",IF(AB42=2,Z42&" * "&AA42,IF(Z42=AA42,"Redondo "&Z42&" * "&AA42,"Ovalado "&Z42&" * "&AA42))) | AY42: =IF(A42=0,"",AG42+AI42+AK42) | AZ42: =IF(A42=0,"",A42) | BA42: =IF(A42=0,"",ROUND(AY42*AZ42,2))
A43: 0 | B43: 1 | D43: 1 | E43: =MATCH(C43,ARTICULOS!$F$10:$F$699,0) | F43: =+VLOOKUP(E43,ARTICULOS!$D$10:$I$699,6) | G43: =+F43&D43 | H43: =+MATCH(G43,COLORES!$E$7:$E$4394,0) | I43: =VLOOKUP(H43,COLORES!$A$7:$I$4394,8) | J43: =VLOOKUP(H43,COLORES!$A$7:$I$4394,9) | K43: =I43*(1+B43) | L43: 0 | M43: 0 | N43: 0 | O43: 0 | P43: 0 | Q43: 0 | S43: =IF(P43>0,IF(O43>0,"(/)"&O43&"*"&P43&IF(Q43>0,"+"&Q43,IF(Q43=0,"",Q43)),+M43&"*"&N43&"*"&P43&IF(Q43>0,"+"&Q43,IF(Q43=0,"",Q43))),"") | T43: =+IF(O43>0,O43+R43*2,M43+R43*2)+P43*2+Q43*2 | U43: =+IF(O43>0,O43+R43*2,N43+R43*2)+P43*2+Q43*2 | W43: =IF(V43=1,T43+5,T43+(V43*4)) | X43: =IF(V43=1,U43+5,U43+(V43*4)) | Y43: 0 | Z43: =IF(Y43=1,ROUNDUP(W43*(1+VLOOKUP(E43,ARTICULOS!$D$10:$H$699,5)),0),W43) | AA43: =IF(Y43=1,ROUNDUP(X43*(1+VLOOKUP(E43,ARTICULOS!$D$10:$H$699,4)),0),X43) | AB43: 2 | AD43: =IF(AC43=1,J43*100&Z43,"") | AE43: =IF(AC43=1,VLOOKUP(AD43,EMPALME!$C$2:$F$33,4),"") | AG43: =IF(L43=3,IF(V43=1,CONFECCION!$C$18,CONFECCION!$C$18*2),IF(V43=1,HLOOKUP(AA43,CONFECCION!$C$17:$AD$33,VLOOKUP(Z43,CONFECCION!$A$18:$B$33,2)-16),2*HLOOKUP(AA43,CONFECCION!$C$17:$AD$33,VLOOKUP(Z43,CONFECCION!$A$18:$B$33,2)-16)))*IF(AC43=1,3,1) | AI43: =IF(AC43=1,AA43/100*K43+IF(AF43>0,K43*(VLOOKUP(AD43,EMPALME!$C$2:$D$33,2)/100)/AF43,K43*(VLOOKUP(AD43,EMPALME!$C$2:$D$33,2)/100)/VLOOKUP(AD43,EMPALME!$C$2:$F$33,4)),IF(AH43=2,ROUND((K43*(AA43/100)-(I43/10)*INT((AA43/100)/0.55)*INT((J43-(Z43/100)*INT(J43/(Z43/100)))/0.55))/INT(J43/(Z43/100)),2),ROUND(K43*(AA43/100)/INT(J43/(Z43/100)),2))) | AJ43: 2 | AK43: =ROUND(IF(AJ43=2,0,((Z43*2)+(AA43*2))*CONFECCION!$B$35/100),2) | AM43: 2 | AQ43: =IF(S43=0,"",S43) | AR43: =IF(A43=0,"",VLOOKUP(L43,ARTICULOS!$A$10:$B$19,2)) | AS43: =IF(A43=0,"",T43&" * "&U43)&IF(AM43=1," PR","") | AT43: =IF(A43=0,"",VLOOKUP(E43,ARTICULOS!$D$10:$F$699,3)) | AU43: =IF(A43=0,"","c/ "&D43&" "&VLOOKUP(H43,COLORES!$A$7:$G$4394,7)) | AV43: =IF(A43=0,"",IF(V43=1,"Dobl. Sencillo","Dobl. "&V43&" cm.")) | AW43: =+IF(Y43=1,"SI","") | AX43: =IF(A43=0,"",IF(AB43=2,Z43&" * "&AA43,IF(Z43=AA43,"Redondo "&Z43&" * "&AA43,"Ovalado "&Z43&" * "&AA43))) | AY43: =IF(A43=0,"",AG43+AI43+AK43) | AZ43: =IF(A43=0,"",A43) | BA43: =IF(A43=0,"",ROUND(AY43*AZ43,2))
A44: 0 | B44: 1 | D44: 1 | E44: =MATCH(C44,ARTICULOS!$F$10:$F$699,0) | F44: =+VLOOKUP(E44,ARTICULOS!$D$10:$I$699,6) | G44: =+F44&D44 | H44: =+MATCH(G44,COLORES!$E$7:$E$4394,0) | I44: =VLOOKUP(H44,COLORES!$A$7:$I$4394,8) | J44: =VLOOKUP(H44,COLORES!$A$7:$I$4394,9) | K44: =I44*(1+B44) | L44: 0 | M44: 0 | N44: 0 | O44: 0 | P44: 0 | Q44: 0 | S44: =IF(P44>0,IF(O44>0,"(/)"&O44&"*"&P44&IF(Q44>0,"+"&Q44,IF(Q44=0,"",Q44)),+M44&"*"&N44&"*"&P44&IF(Q44>0,"+"&Q44,IF(Q44=0,"",Q44))),"") | T44: =+IF(O44>0,O44+R44*2,M44+R44*2)+P44*2+Q44*2 | U44: =+IF(O44>0,O44+R44*2,N44+R44*2)+P44*2+Q44*2 | W44: =IF(V44=1,T44+5,T44+(V44*4)) | X44: =IF(V44=1,U44+5,U44+(V44*4)) | Y44: 0 | Z44: =IF(Y44=1,ROUNDUP(W44*(1+VLOOKUP(E44,ARTICULOS!$D$10:$H$699,5)),0),W44) | AA44: =IF(Y44=1,ROUNDUP(X44*(1+VLOOKUP(E44,ARTICULOS!$D$10:$H$699,4)),0),X44) | AB44: 2 | AD44: =IF(AC44=1,J44*100&Z44,"") | AE44: =IF(AC44=1,VLOOKUP(AD44,EMPALME!$C$2:$F$33,4),"") | AG44: =IF(L44=3,IF(V44=1,CONFECCION!$C$18,CONFECCION!$C$18*2),IF(V44=1,HLOOKUP(AA44,CONFECCION!$C$17:$AD$33,VLOOKUP(Z44,CONFECCION!$A$18:$B$33,2)-16),2*HLOOKUP(AA44,CONFECCION!$C$17:$AD$33,VLOOKUP(Z44,CONFECCION!$A$18:$B$33,2)-16)))*IF(AC44=1,3,1) | AI44: =IF(AC44=1,AA44/100*K44+IF(AF44>0,K44*(VLOOKUP(AD44,EMPALME!$C$2:$D$33,2)/100)/AF44,K44*(VLOOKUP(AD44,EMPALME!$C$2:$D$33,2)/100)/VLOOKUP(AD44,EMPALME!$C$2:$F$33,4)),IF(AH44=2,ROUND((K44*(AA44/100)-(I44/10)*INT((AA44/100)/0.55)*INT((J44-(Z44/100)*INT(J44/(Z44/100)))/0.55))/INT(J44/(Z44/100)),2),ROUND(K44*(AA44/100)/INT(J44/(Z44/100)),2))) | AJ44: 2 | AK44: =ROUND(IF(AJ44=2,0,((Z44*2)+(AA44*2))*CONFECCION!$B$35/100),2) | AM44: 2 | AQ44: =IF(S44=0,"",S44) | AR44: =IF(A44=0,"",VLOOKUP(L44,ARTICULOS!$A$10:$B$19,2)) | AS44: =IF(A44=0,"",T44&" * "&U44)&IF(AM44=1," PR","") | AT44: =IF(A44=0,"",VLOOKUP(E44,ARTICULOS!$D$10:$F$699,3)) | AU44: =IF(A44=0,"","c/ "&D44&" "&VLOOKUP(H44,COLORES!$A$7:$G$4394,7)) | AV44: =IF(A44=0,"",IF(V44=1,"Dobl. Sencillo","Dobl. "&V44&" cm.")) | AW44: =+IF(Y44=1,"SI","") | AX44: =IF(A44=0,"",IF(AB44=2,Z44&" * "&AA44,IF(Z44=AA44,"Redondo "&Z44&" * "&AA44,"Ovalado "&Z44&" * "&AA44))) | AY44: =IF(A44=0,"",AG44+AI44+AK44) | AZ44: =IF(A44=0,"",A44) | BA44: =IF(A44=0,"",ROUND(AY44*AZ44,2))
A45: 0 | B45: 1 | D45: 1 | E45: =MATCH(C45,ARTICULOS!$F$10:$F$699,0) | F45: =+VLOOKUP(E45,ARTICULOS!$D$10:$I$699,6) | G45: =+F45&D45 | H45: =+MATCH(G45,COLORES!$E$7:$E$4394,0) | I45: =VLOOKUP(H45,COLORES!$A$7:$I$4394,8) | J45: =VLOOKUP(H45,COLORES!$A$7:$I$4394,9) | K45: =I45*(1+B45) | L45: 0 | M45: 0 | N45: 0 | O45: 0 | P45: 0 | Q45: 0 | S45: =IF(P45>0,IF(O45>0,"(/)"&O45&"*"&P45&IF(Q45>0,"+"&Q45,IF(Q45=0,"",Q45)),+M45&"*"&N45&"*"&P45&IF(Q45>0,"+"&Q45,IF(Q45=0,"",Q45))),"") | T45: =+IF(O45>0,O45+R45*2,M45+R45*2)+P45*2+Q45*2 | U45: =+IF(O45>0,O45+R45*2,N45+R45*2)+P45*2+Q45*2 | W45: =IF(V45=1,T45+5,T45+(V45*4)) | X45: =IF(V45=1,U45+5,U45+(V45*4)) | Y45: 0 | Z45: =IF(Y45=1,ROUNDUP(W45*(1+VLOOKUP(E45,ARTICULOS!$D$10:$H$699,5)),0),W45) | AA45: =IF(Y45=1,ROUNDUP(X45*(1+VLOOKUP(E45,ARTICULOS!$D$10:$H$699,4)),0),X45) | AB45: 2 | AD45: =IF(AC45=1,J45*100&Z45,"") | AE45: =IF(AC45=1,VLOOKUP(AD45,EMPALME!$C$2:$F$33,4),"") | AG45: =IF(L45=3,IF(V45=1,CONFECCION!$C$18,CONFECCION!$C$18*2),IF(V45=1,HLOOKUP(AA45,CONFECCION!$C$17:$AD$33,VLOOKUP(Z45,CONFECCION!$A$18:$B$33,2)-16),2*HLOOKUP(AA45,CONFECCION!$C$17:$AD$33,VLOOKUP(Z45,CONFECCION!$A$18:$B$33,2)-16)))*IF(AC45=1,3,1) | AI45: =IF(AC45=1,AA45/100*K45+IF(AF45>0,K45*(VLOOKUP(AD45,EMPALME!$C$2:$D$33,2)/100)/AF45,K45*(VLOOKUP(AD45,EMPALME!$C$2:$D$33,2)/100)/VLOOKUP(AD45,EMPALME!$C$2:$F$33,4)),IF(AH45=2,ROUND((K45*(AA45/100)-(I45/10)*INT((AA45/100)/0.55)*INT((J45-(Z45/100)*INT(J45/(Z45/100)))/0.55))/INT(J45/(Z45/100)),2),ROUND(K45*(AA45/100)/INT(J45/(Z45/100)),2))) | AJ45: 2 | AK45: =ROUND(IF(AJ45=2,0,((Z45*2)+(AA45*2))*CONFECCION!$B$35/100),2) | AM45: 2 | AQ45: =IF(S45=0,"",S45) | AR45: =IF(A45=0,"",VLOOKUP(L45,ARTICULOS!$A$10:$B$19,2)) | AS45: =IF(A45=0,"",T45&" * "&U45)&IF(AM45=1," PR","") | AT45: =IF(A45=0,"",VLOOKUP(E45,ARTICULOS!$D$10:$F$699,3)) | AU45: =IF(A45=0,"","c/ "&D45&" "&VLOOKUP(H45,COLORES!$A$7:$G$4394,7)) | AV45: =IF(A45=0,"",IF(V45=1,"Dobl. Sencillo","Dobl. "&V45&" cm.")) | AW45: =+IF(Y45=1,"SI","") | AX45: =IF(A45=0,"",IF(AB45=2,Z45&" * "&AA45,IF(Z45=AA45,"Redondo "&Z45&" * "&AA45,"Ovalado "&Z45&" * "&AA45))) | AY45: =IF(A45=0,"",AG45+AI45+AK45) | AZ45: =IF(A45=0,"",A45) | BA45: =IF(A45=0,"",ROUND(AY45*AZ45,2))
A46: 0 | B46: 1 | D46: 1 | E46: =MATCH(C46,ARTICULOS!$F$10:$F$699,0) | F46: =+VLOOKUP(E46,ARTICULOS!$D$10:$I$699,6) | G46: =+F46&D46 | H46: =+MATCH(G46,COLORES!$E$7:$E$4394,0) | I46: =VLOOKUP(H46,COLORES!$A$7:$I$4394,8) | J46: =VLOOKUP(H46,COLORES!$A$7:$I$4394,9) | K46: =I46*(1+B46) | L46: 0 | M46: 0 | N46: 0 | O46: 0 | P46: 0 | Q46: 0 | S46: =IF(P46>0,IF(O46>0,"(/)"&O46&"*"&P46&IF(Q46>0,"+"&Q46,IF(Q46=0,"",Q46)),+M46&"*"&N46&"*"&P46&IF(Q46>0,"+"&Q46,IF(Q46=0,"",Q46))),"") | T46: =+IF(O46>0,O46+R46*2,M46+R46*2)+P46*2+Q46*2 | U46: =+IF(O46>0,O46+R46*2,N46+R46*2)+P46*2+Q46*2 | W46: =IF(V46=1,T46+5,T46+(V46*4)) | X46: =IF(V46=1,U46+5,U46+(V46*4)) | Y46: 0 | Z46: =IF(Y46=1,ROUNDUP(W46*(1+VLOOKUP(E46,ARTICULOS!$D$10:$H$699,5)),0),W46) | AA46: =IF(Y46=1,ROUNDUP(X46*(1+VLOOKUP(E46,ARTICULOS!$D$10:$H$699,4)),0),X46) | AB46: 2 | AD46: =IF(AC46=1,J46*100&Z46,"") | AE46: =IF(AC46=1,VLOOKUP(AD46,EMPALME!$C$2:$F$33,4),"") | AG46: =IF(L46=3,IF(V46=1,CONFECCION!$C$18,CONFECCION!$C$18*2),IF(V46=1,HLOOKUP(AA46,CONFECCION!$C$17:$AD$33,VLOOKUP(Z46,CONFECCION!$A$18:$B$33,2)-16),2*HLOOKUP(AA46,CONFECCION!$C$17:$AD$33,VLOOKUP(Z46,CONFECCION!$A$18:$B$33,2)-16)))*IF(AC46=1,3,1) | AI46: =IF(AC46=1,AA46/100*K46+IF(AF46>0,K46*(VLOOKUP(AD46,EMPALME!$C$2:$D$33,2)/100)/AF46,K46*(VLOOKUP(AD46,EMPALME!$C$2:$D$33,2)/100)/VLOOKUP(AD46,EMPALME!$C$2:$F$33,4)),IF(AH46=2,ROUND((K46*(AA46/100)-(I46/10)*INT((AA46/100)/0.55)*INT((J46-(Z46/100)*INT(J46/(Z46/100)))/0.55))/INT(J46/(Z46/100)),2),ROUND(K46*(AA46/100)/INT(J46/(Z46/100)),2))) | AJ46: 2 | AK46: =ROUND(IF(AJ46=2,0,((Z46*2)+(AA46*2))*CONFECCION!$B$35/100),2) | AM46: 2 | AQ46: =IF(S46=0,"",S46) | AR46: =IF(A46=0,"",VLOOKUP(L46,ARTICULOS!$A$10:$B$19,2)) | AS46: =IF(A46=0,"",T46&" * "&U46)&IF(AM46=1," PR","") | AT46: =IF(A46=0,"",VLOOKUP(E46,ARTICULOS!$D$10:$F$699,3)) | AU46: =IF(A46=0,"","c/ "&D46&" "&VLOOKUP(H46,COLORES!$A$7:$G$4394,7)) | AV46: =IF(A46=0,"",IF(V46=1,"Dobl. Sencillo","Dobl. "&V46&" cm.")) | AW46: =+IF(Y46=1,"SI","") | AX46: =IF(A46=0,"",IF(AB46=2,Z46&" * "&AA46,IF(Z46=AA46,"Redondo "&Z46&" * "&AA46,"Ovalado "&Z46&" * "&AA46))) | AY46: =IF(A46=0,"",AG46+AI46+AK46) | AZ46: =IF(A46=0,"",A46) | BA46: =IF(A46=0,"",ROUND(AY46*AZ46,2))
A47: 0 | B47: 1 | D47: 1 | E47: =MATCH(C47,ARTICULOS!$F$10:$F$699,0) | F47: =+VLOOKUP(E47,ARTICULOS!$D$10:$I$699,6) | G47: =+F47&D47 | H47: =+MATCH(G47,COLORES!$E$7:$E$4394,0) | I47: =VLOOKUP(H47,COLORES!$A$7:$I$4394,8) | J47: =VLOOKUP(H47,COLORES!$A$7:$I$4394,9) | K47: =I47*(1+B47) | L47: 0 | M47: 0 | N47: 0 | O47: 0 | P47: 0 | Q47: 0 | S47: =IF(P47>0,IF(O47>0,"(/)"&O47&"*"&P47&IF(Q47>0,"+"&Q47,IF(Q47=0,"",Q47)),+M47&"*"&N47&"*"&P47&IF(Q47>0,"+"&Q47,IF(Q47=0,"",Q47))),"") | T47: =+IF(O47>0,O47+R47*2,M47+R47*2)+P47*2+Q47*2 | U47: =+IF(O47>0,O47+R47*2,N47+R47*2)+P47*2+Q47*2 | W47: =IF(V47=1,T47+5,T47+(V47*4)) | X47: =IF(V47=1,U47+5,U47+(V47*4)) | Y47: 0 | Z47: =IF(Y47=1,ROUNDUP(W47*(1+VLOOKUP(E47,ARTICULOS!$D$10:$H$699,5)),0),W47) | AA47: =IF(Y47=1,ROUNDUP(X47*(1+VLOOKUP(E47,ARTICULOS!$D$10:$H$699,4)),0),X47) | AB47: 2 | AD47: =IF(AC47=1,J47*100&Z47,"") | AE47: =IF(AC47=1,VLOOKUP(AD47,EMPALME!$C$2:$F$33,4),"") | AG47: =IF(L47=3,IF(V47=1,CONFECCION!$C$18,CONFECCION!$C$18*2),IF(V47=1,HLOOKUP(AA47,CONFECCION!$C$17:$AD$33,VLOOKUP(Z47,CONFECCION!$A$18:$B$33,2)-16),2*HLOOKUP(AA47,CONFECCION!$C$17:$AD$33,VLOOKUP(Z47,CONFECCION!$A$18:$B$33,2)-16)))*IF(AC47=1,3,1) | AI47: =IF(AC47=1,AA47/100*K47+IF(AF47>0,K47*(VLOOKUP(AD47,EMPALME!$C$2:$D$33,2)/100)/AF47,K47*(VLOOKUP(AD47,EMPALME!$C$2:$D$33,2)/100)/VLOOKUP(AD47,EMPALME!$C$2:$F$33,4)),IF(AH47=2,ROUND((K47*(AA47/100)-(I47/10)*INT((AA47/100)/0.55)*INT((J47-(Z47/100)*INT(J47/(Z47/100)))/0.55))/INT(J47/(Z47/100)),2),ROUND(K47*(AA47/100)/INT(J47/(Z47/100)),2))) | AJ47: 2 | AK47: =ROUND(IF(AJ47=2,0,((Z47*2)+(AA47*2))*CONFECCION!$B$35/100),2) | AM47: 2 | AQ47: =IF(S47=0,"",S47) | AR47: =IF(A47=0,"",VLOOKUP(L47,ARTICULOS!$A$10:$B$19,2)) | AS47: =IF(A47=0,"",T47&" * "&U47)&IF(AM47=1," PR","") | AT47: =IF(A47=0,"",VLOOKUP(E47,ARTICULOS!$D$10:$F$699,3)) | AU47: =IF(A47=0,"","c/ "&D47&" "&VLOOKUP(H47,COLORES!$A$7:$G$4394,7)) | AV47: =IF(A47=0,"",IF(V47=1,"Dobl. Sencillo","Dobl. "&V47&" cm.")) | AW47: =+IF(Y47=1,"SI","") | AX47: =IF(A47=0,"",IF(AB47=2,Z47&" * "&AA47,IF(Z47=AA47,"Redondo "&Z47&" * "&AA47,"Ovalado "&Z47&" * "&AA47))) | AY47: =IF(A47=0,"",AG47+AI47+AK47) | AZ47: =IF(A47=0,"",A47) | BA47: =IF(A47=0,"",ROUND(AY47*AZ47,2))
A48: 0 | B48: 1 | D48: 1 | E48: =MATCH(C48,ARTICULOS!$F$10:$F$699,0) | F48: =+VLOOKUP(E48,ARTICULOS!$D$10:$I$699,6) | G48: =+F48&D48 | H48: =+MATCH(G48,COLORES!$E$7:$E$4394,0) | I48: =VLOOKUP(H48,COLORES!$A$7:$I$4394,8) | J48: =VLOOKUP(H48,COLORES!$A$7:$I$4394,9) | K48: =I48*(1+B48) | L48: 0 | M48: 0 | N48: 0 | O48: 0 | P48: 0 | Q48: 0 | S48: =IF(P48>0,IF(O48>0,"(/)"&O48&"*"&P48&IF(Q48>0,"+"&Q48,IF(Q48=0,"",Q48)),+M48&"*"&N48&"*"&P48&IF(Q48>0,"+"&Q48,IF(Q48=0,"",Q48))),"") | T48: =+IF(O48>0,O48+R48*2,M48+R48*2)+P48*2+Q48*2 | U48: =+IF(O48>0,O48+R48*2,N48+R48*2)+P48*2+Q48*2 | W48: =IF(V48=1,T48+5,T48+(V48*4)) | X48: =IF(V48=1,U48+5,U48+(V48*4)) | Y48: 0 | Z48: =IF(Y48=1,ROUNDUP(W48*(1+VLOOKUP(E48,ARTICULOS!$D$10:$H$699,5)),0),W48) | AA48: =IF(Y48=1,ROUNDUP(X48*(1+VLOOKUP(E48,ARTICULOS!$D$10:$H$699,4)),0),X48) | AB48: 2 | AD48: =IF(AC48=1,J48*100&Z48,"") | AE48: =IF(AC48=1,VLOOKUP(AD48,EMPALME!$C$2:$F$33,4),"") | AG48: =IF(L48=3,IF(V48=1,CONFECCION!$C$18,CONFECCION!$C$18*2),IF(V48=1,HLOOKUP(AA48,CONFECCION!$C$17:$AD$33,VLOOKUP(Z48,CONFECCION!$A$18:$B$33,2)-16),2*HLOOKUP(AA48,CONFECCION!$C$17:$AD$33,VLOOKUP(Z48,CONFECCION!$A$18:$B$33,2)-16)))*IF(AC48=1,3,1) | AI48: =IF(AC48=1,AA48/100*K48+IF(AF48>0,K48*(VLOOKUP(AD48,EMPALME!$C$2:$D$33,2)/100)/AF48,K48*(VLOOKUP(AD48,EMPALME!$C$2:$D$33,2)/100)/VLOOKUP(AD48,EMPALME!$C$2:$F$33,4)),IF(AH48=2,ROUND((K48*(AA48/100)-(I48/10)*INT((AA48/100)/0.55)*INT((J48-(Z48/100)*INT(J48/(Z48/100)))/0.55))/INT(J48/(Z48/100)),2),ROUND(K48*(AA48/100)/INT(J48/(Z48/100)),2))) | AJ48: 2 | AK48: =ROUND(IF(AJ48=2,0,((Z48*2)+(AA48*2))*CONFECCION!$B$35/100),2) | AM48: 2 | AQ48: =IF(S48=0,"",S48) | AR48: =IF(A48=0,"",VLOOKUP(L48,ARTICULOS!$A$10:$B$19,2)) | AS48: =IF(A48=0,"",T48&" * "&U48)&IF(AM48=1," PR","") | AT48: =IF(A48=0,"",VLOOKUP(E48,ARTICULOS!$D$10:$F$699,3)) | AU48: =IF(A48=0,"","c/ "&D48&" "&VLOOKUP(H48,COLORES!$A$7:$G$4394,7)) | AV48: =IF(A48=0,"",IF(V48=1,"Dobl. Sencillo","Dobl. "&V48&" cm.")) | AW48: =+IF(Y48=1,"SI","") | AX48: =IF(A48=0,"",IF(AB48=2,Z48&" * "&AA48,IF(Z48=AA48,"Redondo "&Z48&" * "&AA48,"Ovalado "&Z48&" * "&AA48))) | AY48: =IF(A48=0,"",AG48+AI48+AK48) | AZ48: =IF(A48=0,"",A48) | BA48: =IF(A48=0,"",ROUND(AY48*AZ48,2))
A49: 0 | B49: 1 | D49: 1 | E49: =MATCH(C49,ARTICULOS!$F$10:$F$699,0) | F49: =+VLOOKUP(E49,ARTICULOS!$D$10:$I$699,6) | G49: =+F49&D49 | H49: =+MATCH(G49,COLORES!$E$7:$E$4394,0) | I49: =VLOOKUP(H49,COLORES!$A$7:$I$4394,8) | J49: =VLOOKUP(H49,COLORES!$A$7:$I$4394,9) | K49: =I49*(1+B49) | L49: 0 | M49: 0 | N49: 0 | O49: 0 | P49: 0 | Q49: 0 | S49: =IF(P49>0,IF(O49>0,"(/)"&O49&"*"&P49&IF(Q49>0,"+"&Q49,IF(Q49=0,"",Q49)),+M49&"*"&N49&"*"&P49&IF(Q49>0,"+"&Q49,IF(Q49=0,"",Q49))),"") | T49: =+IF(O49>0,O49+R49*2,M49+R49*2)+P49*2+Q49*2 | U49: =+IF(O49>0,O49+R49*2,N49+R49*2)+P49*2+Q49*2 | W49: =IF(V49=1,T49+5,T49+(V49*4)) | X49: =IF(V49=1,U49+5,U49+(V49*4)) | Y49: 0 | Z49: =IF(Y49=1,ROUNDUP(W49*(1+VLOOKUP(E49,ARTICULOS!$D$10:$H$699,5)),0),W49) | AA49: =IF(Y49=1,ROUNDUP(X49*(1+VLOOKUP(E49,ARTICULOS!$D$10:$H$699,4)),0),X49) | AB49: 2 | AD49: =IF(AC49=1,J49*100&Z49,"") | AE49: =IF(AC49=1,VLOOKUP(AD49,EMPALME!$C$2:$F$33,4),"") | AG49: =IF(L49=3,IF(V49=1,CONFECCION!$C$18,CONFECCION!$C$18*2),IF(V49=1,HLOOKUP(AA49,CONFECCION!$C$17:$AD$33,VLOOKUP(Z49,CONFECCION!$A$18:$B$33,2)-16),2*HLOOKUP(AA49,CONFECCION!$C$17:$AD$33,VLOOKUP(Z49,CONFECCION!$A$18:$B$33,2)-16)))*IF(AC49=1,3,1) | AI49: =IF(AC49=1,AA49/100*K49+IF(AF49>0,K49*(VLOOKUP(AD49,EMPALME!$C$2:$D$33,2)/100)/AF49,K49*(VLOOKUP(AD49,EMPALME!$C$2:$D$33,2)/100)/VLOOKUP(AD49,EMPALME!$C$2:$F$33,4)),IF(AH49=2,ROUND((K49*(AA49/100)-(I49/10)*INT((AA49/100)/0.55)*INT((J49-(Z49/100)*INT(J49/(Z49/100)))/0.55))/INT(J49/(Z49/100)),2),ROUND(K49*(AA49/100)/INT(J49/(Z49/100)),2))) | AJ49: 2 | AK49: =ROUND(IF(AJ49=2,0,((Z49*2)+(AA49*2))*CONFECCION!$B$35/100),2) | AM49: 2 | AQ49: =IF(S49=0,"",S49) | AR49: =IF(A49=0,"",VLOOKUP(L49,ARTICULOS!$A$10:$B$19,2)) | AS49: =IF(A49=0,"",T49&" * "&U49)&IF(AM49=1," PR","") | AT49: =IF(A49=0,"",VLOOKUP(E49,ARTICULOS!$D$10:$F$699,3)) | AU49: =IF(A49=0,"","c/ "&D49&" "&VLOOKUP(H49,COLORES!$A$7:$G$4394,7)) | AV49: =IF(A49=0,"",IF(V49=1,"Dobl. Sencillo","Dobl. "&V49&" cm.")) | AW49: =+IF(Y49=1,"SI","") | AX49: =IF(A49=0,"",IF(AB49=2,Z49&" * "&AA49,IF(Z49=AA49,"Redondo "&Z49&" * "&AA49,"Ovalado "&Z49&" * "&AA49))) | AY49: =IF(A49=0,"",AG49+AI49+AK49) | AZ49: =IF(A49=0,"",A49) | BA49: =IF(A49=0,"",ROUND(AY49*AZ49,2))
AY51: TOTAL PRESUPUESTO | BA51: =ROUND(SUM(BA10:BA49),2)

Sheet ARTICULOS
D6: ¡¡¡¡NO PONGAS ACENTOS !!!!!!
A8: PRODUCTO | D8: ARTICULO
D9: REF. 1 | G9: Encogimiento LargoU | H9: Encogimiento AnchoT | I9: REF. 2
A10: 1 | B10: Mantel | D10: 1 | E10: TVR | F10: Saten 50/50 | G10: 0.03 | H10: 0.02 | I10: =+D10&E10
A11: 2 | B11: Cubre | D11: 2 | E11: TVR | F11: Saten Pes100 | G11: 0 | H11: 0 | I11: =+D11&E11
A12: 3 | B12: Servilleta | D12: 3 | E12: TVR | F12: Saten London | G12: 0 | H12: 0 | I12: =+D12&E12
A13: 4 | B13: Camino de mesa | C13: Triana | D13: 4 | E13: TVR | F13: Triunfo | G13: 0.03 | H13: 0.02 | I13: =+D13&E13
A14: 5 | B14: Muleton | C14: Triana Imitacion | D14: 5 | E14: TVR | F14: Triunfo Lino | G14: 0.03 | H14: 0.02 | I14: =+D14&E14
A15: 6 | B15: Gueridon | D15: 6 | E15: TVR | F15: Granito | G15: 0 | H15: 0 | I15: =+D15&E15
A16: 7 | B16: Lito | D16: 7 | E16: TVR | F16: Tevere | G16: 0.03 | H16: 0.02 | I16: =+D16&E16
A17: 8 | B17: Individual | D17: 8 | E17: TVR | F17: Tagore Pes100 | G17: 0 | H17: 0 | I17: =+D17&E17
A18: 9 | D18: 9 | E18: TVR | F18: Santorini | G18: 0 | H18: 0 | I18: =+D18&E18
A19: 10 | B19: Funda | C19: Jara | D19: 10 | E19: TVR | F19: Lino Jazmin | G19: 0.03 | H19: 0.05 | I19: =+D19&E19
D20: 11 | E20: TVR | F20: Damasco Alhambra | G20: 0.03 | H20: 0.02 | I20: =+D20&E20
D21: 12 | E21: GRT | F21: Nilo Rustico | G21: 0.045 | H21: 0.035 | I21: =+D21&E21 | J21: 2024
D22: 13 | E22: GRT | F22: Lino Grt | G22: 0.05 | H22: 0.05 | I22: =+D22&E22 | J22: 2024 | K22: al/lin/pol
D23: 14 | E23: RMR | F23: Acrisol Liso 160 | G23: 0 | H23: 0 | I23: =+D23&E23
D24: 15 | E24: RMR | F24: Acrisol Liso 320 | G24: 0 | H24: 0 | I24: =+D24&E24
D25: 16 | E25: RMR | F25: Acrisol 7 Calles 160 | G25: 0 | H25: 0 | I25: =+D25&E25
D26: 17 | E26: GCU | F26: LinoPoliester | G26: 0.03 | H26: 0.02 | I26: =+D26&E26
D27: 18 | E27: TVR | F27: Saten London | G27: 0 | H27: 0 | I27: =+D27&E27
D28: 19 | E28: GCU | F28: Saten Liso Nacional | G28: 0.03 | H28: 0.02 | I28: =+D28&E28
D29: 20 | E29: TVR | F29: Saten Liso Importacion | G29: 0.03 | H29: 0.02 | I29: =+D29&E29
D30: 21 | E30: TVR | F30: Chambery | G30: 0.03 | H30: 0.02 | I30: =+D30&E30 | J30: ojo modificado según lavado miguel 2025
D31: 22 | E31: TVR | F31: Rabat | G31: 0.06 | H31: 0.04 | I31: =+D31&E31
D32: 23 | E32: ANG | F32: Lino 100% For. | G32: 0.067 | H32: 0.055 | I32: =+D32&E32
D33: 24 | E33: GRT | F33: Muleton | G33: 0 | H33: 0 | I33: =+D33&E33
D34: 25 | E34: TVR | F34: Col. Rustico T. | G34: 0 | H34: 0 | I34: =+D34&E34
D35: 26 | E35: BTX | F35: Clio | G35: 0.02 | H35: 0.02 | I35: =+D35&E35
D36: 27 | E36: GCU | F36: Nilo Cuadro | G36: 0.035 | H36: 0.03 | I36: =+D36&E36
D37: 28 | E37: YEB | F37: Fenicia | G37: 0.025 | H37: 0.02 | I37: =+D37&E37
D38: 29 | E38: TVR | F38: Mahon | G38: 0.02 | H38: 0.02 | I38: =+D38&E38
D39: 30 | E39: BTX | F39: Gouble | G39: 0.02 | H39: 0.02 | I39: =+D39&E39
D40: 31 | E40: BTX | F40: Trivial | G40: 0.02 | H40: 0.02 | I40: =+D40&E40
D41: 32 | E41: GCU | F41: Resite Antimanchas | G41: 0 | H41: 0 | I41: =+D41&E41
D42: 33 | E42: TVR | F42: Saten Antimanchas | G42: 0.01 | H42: 0.01 | I42: =+D42&E42
... D51: 42 | E51: TVR | F51: Santorini | G51: 0.01 | H51: 0.01 | I51: =+D51&E51
D52: 43 | E52: COM | F52: Aeris | I52: =+D52&E52
D53: 44 | E53: GRT | F53: Recy Linen | G53: 0.055 | H53: 0.035 | I53: =+D53&E53 | J53: 2024
D54: 45 | E54: YEB | F54: Bellini | G54: 0 | H54: 0 | I54: =+D54&E54
D55: 46 | E55: RMA | F55: Ninfa | G55: 0 | H55: 0 | I55: =+D55&E55
D56: 47 | E56: GCU | F56: Saten Algodon | G56: 0.055 | H56: 0.035 | I56: =+D56&E56
D57: 48 | E57: YEB | F57: Lido | G57: 0.02 | H57: 0.02 | I57: =+D57&E57
D58: 49 | E58: MRV | F58: Baroja | G58: 0 | H58: 0 | I58: =+D58&E58
D59: 50 | I59: =+D59&E59
D60: 51 | I60: =+D60&E60
D61: 52 | I61: =+D61&E61
D62: 53 | I62: =+D62&E62
D63: 54 | I63: =+D63&E63
D64: 55 | I64: =+D64&E64
D65: 56 | I65: =+D65&E65
D66: 57 | I66: =+D66&E66
D67: 58 | I67: =+D67&E67
D68: 59 | I68: =+D68&E68
D69: 60 | I69: =+D69&E69
D70: 61 | I70: =+D70&E70
... D218: 209 | I218: =+D218&E218
B219: Algodn / lino | D219: 210 | I219: =+D219&E219
D220: 211 | I220: =+D220&E220
A221: NOTA.- PORCENTAJE A QUITAR SI ES 25 | D221: 212 | I221: =+D221&E221
A222: ES 0.75 | D222: 213 | I222: =+D222&E222
D223: 214 | I223: =+D223&E223
A224: para poner 1,25 | D224: 215 | I224: =+D224&E224
D225: 216 | I225: =+D225&E225
D226: 217 | I226: =+D226&E226
D227: 218 | I227: =+D227&E227
D228: 219 | I228: =+D228&E228
D229: 220 | I229: =+D229&E229
D230: 221 | I230: =+D230&E230
D231: 222 | I231: =+D231&E231
D232: 223 | I232: =+D232&E232
D233: 224 | I233: =+D233&E233
D234: 225 | I234: =+D234&E234
D235: 226 | I235: =+D235&E235
D236: 227 | I236: =+D236&E236
... D699: 690 | I699: =+D699&E699

Sheet COLORES
A6: FILA | B6: REF. 1 | C6: REF. 2 | D6: Artículo | E6: REF. 3 | F6: COLOR | H6: COSTE | I6: ANCHO | J6: COMPOSICION
A7: =ROW()-6 | B7: 1 | C7: =+VLOOKUP(B7,ARTICULOS!$D$10:$I$699,6) | D7: Saten 50/50 | E7: =+C7&F7 | F7: 1 | G7: Blanco | H7: 8.41 | I7: 3.2 | J7: 50% Alg./50%Pes.
A8: =ROW()-6 | B8: =+MATCH(D8,ARTICULOS!$F$10:$F$699,0) | C8: =+VLOOKUP(B8,ARTICULOS!$D$10:$I$699,6) | D8: Saten 50/50 | E8: =+C8&F8 | F8: 2 | G8: Palido | H8: 11.06 | I8: 3.2 | J8: 50% Alg./50%Pes.
A9: =ROW()-6 | B9: =+MATCH(D9,ARTICULOS!$F$10:$F$699,0) | C9: =+VLOOKUP(B9,ARTICULOS!$D$10:$I$699,6) | D9: Saten 50/50 | E9: =+C9&F9 | F9: 3 | G9: Medio | H9: 12.2 | I9: 3.2 | J9: 50% Alg./50%Pes.
A10: =ROW()-6 | B10: =+MATCH(D10,ARTICULOS!$F$10:$F$699,0) | C10: =+VLOOKUP(B10,ARTICULOS!$D$10:$I$699,6) | D10: Saten 50/50 | E10: =+C10&F10 | F10: 4 | G10: Intenso | H10: 13.46 | I10: 3.2 | J10: 50% Alg./50%Pes.
A11: =ROW()-6 | B11: =+MATCH(D11,ARTICULOS!$F$10:$F$699,0) | C11: =+VLOOKUP(B11,ARTICULOS!$D$10:$I$699,6) | D11: Saten 50/50 | E11: =+C11&F11 | F11: 5 | G11: Intenso Especial | H11: 14.55 | I11: 3.2 | J11: 50% Alg./50%Pes.
A12: =ROW()-6 | B12: =+MATCH(D12,ARTICULOS!$F$10:$F$699,0) | C12: =+VLOOKUP(B12,ARTICULOS!$D$10:$I$699,6) | D12: Saten Pes100 | E12: =+C12&F12 | F12: 1 | G12: Blanco | H12: 7.8 | I12: 3.25 | J12: 100% Poliester
A13: =ROW()-6 | B13: =+MATCH(D13,ARTICULOS!$F$10:$F$699,0) | C13: =+VLOOKUP(B13,ARTICULOS!$D$10:$I$699,6) | D13: Saten Pes100 | E13: =+C13&F13 | F13: 2 | G13: Palido | H13: 9.29 | I13: 3.25 | J13: 100% Poliester
A14: =ROW()-6 | B14: =+MATCH(D14,ARTICULOS!$F$10:$F$699,0) | C14: =+VLOOKUP(B14,ARTICULOS!$D$10:$I$699,6) | D14: Saten Pes100 | E14: =+C14&F14 | F14: 3 | G14: Medio | H14: 9.87 | I14: 3.25 | J14: 100% Poliester
A15: =ROW()-6 | B15: =+MATCH(D15,ARTICULOS!$F$10:$F$699,0) | C15: =+VLOOKUP(B15,ARTICULOS!$D$10:$I$699,6) | D15: Saten Pes100 | E15: =+C15&F15 | F15: 4 | G15: Intenso | H15: 11.4 | I15: 3.25 | J15: 100% Poliester
A16: =ROW()-6 | B16: =+MATCH(D16,ARTICULOS!$F$10:$F$699,0) | C16: =+VLOOKUP(B16,ARTICULOS!$D$10:$I$699,6) | D16: Saten London | E16: =+C16&F16 | F16: 1 | G16: Blanco | H16: 9.93 | I16: 3.4 | J16: 100% Poliester
A17: =ROW()-6 | B17: =+MATCH(D17,ARTICULOS!$F$10:$F$699,0) | C17: =+VLOOKUP(B17,ARTICULOS!$D$10:$I$699,6) | D17: Saten London | E17: =+C17&F17 | F17: 2 | G17: Palido | H17: 11.29 | I17: 3.4 | J17: 100% Poliester
A18: =ROW()-6 | B18: =+MATCH(D18,ARTICULOS!$F$10:$F$699,0) | C18: =+VLOOKUP(B18,ARTICULOS!$D$10:$I$699,6) | D18: Saten London | E18: =+C18&F18 | F18: 3 | G18: Medio | H18: 11.44 | I18: 3.4 | J18: 100% Poliester
A19: =ROW()-6 | B19: =+MATCH(D19,ARTICULOS!$F$10:$F$699,0) | C19: =+VLOOKUP(B19,ARTICULOS!$D$10:$I$699,6) | D19: Saten London | E19: =+C19&F19 | F19: 4 | G19: Intenso | H19: 12.67 | I19: 3.4 | J19: 100% Poliester
... A45: =ROW()-6 | B45: =+MATCH(D45,ARTICULOS!$F$10:$F$699,0) | C45: =+VLOOKUP(B45,ARTICULOS!$D$10:$I$699,6) | D45: Clio | E45: =+C45&F45 | F45: 15 | G45: Rojo | H45: 6.76 | I45: 2.8 | J45: 62%Alg. / 38% Pes.
A46: =ROW()-6 | B46: 27 | C46: =+VLOOKUP(B46,ARTICULOS!$D$10:$I$699,6) | D46: Nilo cuadro | E46: =+C46&F46 | F46: 1 | G46: Blanco | H46: 7.22 | I46: 3.3 | J46: 50% Alg./50%Pes.
A47: =ROW()-6 | B47: 27 | C47: =+VLOOKUP(B47,ARTICULOS!$D$10:$I$699,6) | D47: Nilo cuadro | E47: =+C47&F47 | F47: 2 | G47: Salmon | H47: 9.29 | I47: 3.3 | J47: 50% Alg./50%Pes.
A48: =ROW()-6 | B48: =+MATCH(D48,ARTICULOS!$F$10:$F$699,0) | C48: =+VLOOKUP(B48,ARTICULOS!$D$10:$I$699,6) | D48: Rustico | E48: =+C48&F48 | F48: 2 | G48: Tostado | H48: 8.3 | I48: 2.8 | J48: 100% Poliester
A49: =ROW()-6 | B49: =+MATCH(D49,ARTICULOS!$F$10:$F$699,0) | C49: =+VLOOKUP(B49,ARTICULOS!$D$10:$I$699,6) | D49: Saten Liso Poliester H | E49: =+C49&F49 | F49: 11 | G49: Negro | H49: 8.3 | I49: 3.3 | J49: 100% Poliester
A50: =ROW()-6 | B50: =+MATCH(D50,ARTICULOS!$F$10:$F$699,0) | C50: =+VLOOKUP(B50,ARTICULOS!$D$10:$I$699,6) | D50: Saten Liso Nacional | E50: =+C50&F50 | F50: 53 | H50: 8.71 | I50: 3.3 | J50: 50% Alg./50%Pes.
A51: =ROW()-6 | B51: =+MATCH(D51,ARTICULOS!$F$10:$F$699,0) | C51: =+VLOOKUP(B51,ARTICULOS!$D$10:$I$699,6) | D51: Saten Liso Nacional | E51: =+C51&F51 | F51: 59 | H51: 8.86 | I51: 3.3 | J51: 50% Alg./50%Pes.
A52: =ROW()-6 | B52: =+MATCH(D52,ARTICULOS!$F$10:$F$699,0) | C52: =+VLOOKUP(B52,ARTICULOS!$D$10:$I$699,6) | D52: Fenicia | E52: =+C52&F52 | F52: 1 | G52: Todos los colores | H52: 12.7 | I52: 2.8 | J52: 70%Visc./30% Lino
A53: =ROW()-6 | B53: =+MATCH(D53,ARTICULOS!$F$10:$F$699,0) | C53: =+VLOOKUP(B53,ARTICULOS!$D$10:$I$699,6) | D53: LinoPoliester | E53: =+C53&F53 | F53: 4 | G53: Ocre | H53: 13.41 | I53: 3.3 | J53: 50% Lino/50%Pes.
A54: =ROW()-6 | B54: =+MATCH(D54,ARTICULOS!$F$10:$F$699,0) | C54: =+VLOOKUP(B54,ARTICULOS!$D$10:$I$699,6) | D54: Mahon | E54: =+C54&F54 | F54: 1 | G54: Blanco | H54: 4.36 | I54: 2.8 | J54: 50% Alg./50%Pes.
A55: =ROW()-6 | B55: =+MATCH(D55,ARTICULOS!$F$10:$F$699,0) | C55: =+VLOOKUP(B55,ARTICULOS!$D$10:$I$699,6) | D55: Gouble | E55: =+C55&F55 | F55: 1 | G55: Crudo | H55: 6.76 | I55: 2.8 | J55: 50% Alg./50%Pes.
A56: =ROW()-6 | B56: =+MATCH(D56,ARTICULOS!$F$10:$F$699,0) | C56: =+VLOOKUP(B56,ARTICULOS!$D$10:$I$699,6) | D56: Trivial | E56: =+C56&F56 | F56: 6 | G56: Crudo | H56: 6.76 | I56: 2.8 | J56: 50% Alg./50%Pes.
A57: =ROW()-6 | B57: =+MATCH(D57,ARTICULOS!$F$10:$F$699,0) | C57: =+VLOOKUP(B57,ARTICULOS!$D$10:$I$699,6) | D57: Saten Liso Poliester H | E57: =+C57&F57 | F57: 1 | G57: Blanco | H57: 5.96 | I57: 3.3 | J57: 100% Poliester
A58: =ROW()-6 | B58: =+MATCH(D58,ARTICULOS!$F$10:$F$699,0) | C58: =+VLOOKUP(B58,ARTICULOS!$D$10:$I$699,6) | D58: Saten Liso Nacional | E58: =+C58&F58 | F58: 69 | G58: Cuerda | H58: 8.71 | I58: 3.3 | J58: 50% Alg./50%Pes.
A59: =ROW()-6 | B59: =+MATCH(D59,ARTICULOS!$F$10:$F$699,0) | C59: =+VLOOKUP(B59,ARTICULOS!$D$10:$I$699,6) | D59: Santorini | E59: =+C59&F59 | F59: 1 | G59: Todos los colores | H59: 11.64 | I59: 3.5 | J59: 100% Poliester
A60: =ROW()-6 | B60: =+MATCH(D60,ARTICULOS!$F$10:$F$699,0) | C60: =+VLOOKUP(B60,ARTICULOS!$D$10:$I$699,6) | D60: Aeris | E60: =+C60&F60 | F60: 1 | G60: Todos los colores | H60: 12.56 | I60: 2.8 | J60: 100% Poliester
A61: =ROW()-6 | B61: =+MATCH(D61,ARTICULOS!$F$10:$F$699,0) | C61: =+VLOOKUP(B61,ARTICULOS!$D$10:$I$699,6) | D61: Saten Liso Nacional | E61: =+C61&F61 | F61: 58 | G61: Azul | H61: 9.16 | I61: 3.3 | J61: 50% Alg./50%Pes.
A62: =ROW()-6 | B62: =+MATCH(D62,ARTICULOS!$F$10:$F$699,0) | C62: =+VLOOKUP(B62,ARTICULOS!$D$10:$I$699,6) | D62: LinoPoliester | E62: =+C62&F62 | F62: 1 | G62: Blanco | H62: 12.26 | I62: 3.3
A63: =ROW()-6 | B63: 44 | C63: =+VLOOKUP(B63,ARTICULOS!$D$10:$I$699,6) | D63: Recy Line | E63: =+C63&F63 | F63: 1 | G63: Blanco | H63: 10.82 | I63: 3.4 | J63: 50% Alg./50%Pes. | K63: 2024
A64: =ROW()-6 | B64: 44 | C64: =+VLOOKUP(B64,ARTICULOS!$D$10:$I$699,6) | D64: Recy Line | E64: =+C64&F64 | F64: 2 | G64: Nature | H64: 11 | I64: 3.4 | J64: 50% Alg./50%Pes. | K64: 2024
A65: =ROW()-6 | B65: 44 | C65: =+VLOOKUP(B65,ARTICULOS!$D$10:$I$699,6) | D65: Recy Line | E65: =+C65&F65 | F65: 3 | G65: Caliza | H65: 11.32 | I65: 3.4 | J65: 50% Alg./50%Pes. | K65: 2024
A66: =ROW()-6 | B66: 44 | C66: =+VLOOKUP(B66,ARTICULOS!$D$10:$I$699,6) | D66: Recy Line | E66: =+C66&F66 | F66: 4 | G66: Gris Titanio | H66: 11.32 | I66: 3.4 | J66: 50% Alg./50%Pes. | K66: 2024
A67: =ROW()-6 | B67: 44 | C67: =+VLOOKUP(B67,ARTICULOS!$D$10:$I$699,6) | D67: Recy Line | E67: =+C67&F67 | F67: 5 | G67: Salvaje | H67: 11.65 | I67: 3.4 | J67: 50% Alg./50%Pes. | K67: 2024
A68: =ROW()-6 | B68: 44 | C68: =+VLOOKUP(B68,ARTICULOS!$D$10:$I$699,6) | D68: Recy Line | E68: =+C68&F68 | F68: 6 | G68: Gris Marengo | H68: 11.65 | I68: 3.4 | J68: 50% Alg./50%Pes. | K68: 2024
A69: =ROW()-6 | B69: 12 | C69: =+VLOOKUP(B69,ARTICULOS!$D$10:$I$699,6) | D69: Nilo Rustico | E69: =+C69&F69 | F69: 6 | G69: Gris Marengo | H69: 17.35 | I69: 3.4 | J69: 50%Lin./50%Pes. | K69: 2024
A70: =ROW()-6 | B70: 12 | C70: =+VLOOKUP(B70,ARTICULOS!$D$10:$I$699,6) | D70: Nilo Rustico | E70: =+C70&F70 | F70: 5 | G70: Salvaje | H70: 17.35 | I70: 3.4 | J70: 50%Lin./50%Pes. | K70: 2024
A71: =ROW()-6 | B71: 12 | C71: =+VLOOKUP(B71,ARTICULOS!$D$10:$I$699,6) | D71: Nilo Rustico | E71: =+C71&F71 | F71: 4 | G71: Caliza | H71: 17.35 | I71: 3.4 | J71: 50%Lin./50%Pes. | K71: 2024
A72: =ROW()-6 | B72: 12 | C72: =+VLOOKUP(B72,ARTICULOS!$D$10:$I$699,6) | D72: Nilo Rustico | E72: =+C72&F72 | F72: 3 | G72: Nature | H72: 17.35 | I72: 3.4 | J72: 50%Lin./50%Pes. | K72: 2024
A73: =ROW()-6 | B73: 12 | C73: =+VLOOKUP(B73,ARTICULOS!$D$10:$I$699,6) | D73: Nilo Rustico | E73: =+C73&F73 | F73: 2 | G73: Blanco Quimico | H73: 16.53 | I73: 3.4 | J73: 50%Lin./50%Pes. | K73: 2024
A74: =ROW()-6 | B74: 12 | C74: =+VLOOKUP(B74,ARTICULOS!$D$10:$I$699,6) | D74: Nilo Rustico | E74: =+C74&F74 | F74: 1 | G74: Blanco | H74: 16.53 | I74: 3.4 | J74: 50%Lin./50%Pes. | K74: 2024
... A79: =ROW()-6 | B79: 13 | C79: =+VLOOKUP(B79,ARTICULOS!$D$10:$I$699,6) | D79: Lino Grt | E79: =+C79&F79 | F79: 5 | G79: Chocolate | H79: 11.17 | I79: 3.4 | J79: 40%Alg.10%Lin.50%Pol | K79: 2024
A80: =ROW()-6 | B80: =+MATCH(D80,ARTICULOS!$F$10:$F$699,0) | C80: =+VLOOKUP(B80,ARTICULOS!$D$10:$I$699,6) | D80: Saten Liso Nacional | E80: =+C80&F80 | F80: 70 | G80: Azul Marino | H80: 9.7 | I80: 3.3 | J80: 50% Alg./50%Pes.
A81: =ROW()-6 | B81: =+MATCH(D81,ARTICULOS!$F$10:$F$699,0) | C81: =+VLOOKUP(B81,ARTICULOS!$D$10:$I$699,6) | D81: Saten Liso Poliester H | E81: =+C81&F81 | F81: 19 | G81: Azul Marino | H81: 8.3 | I81: 3.3 | J81: 100% Poliester
A82: =ROW()-6 | B82: =+MATCH(D82,ARTICULOS!$F$10:$F$699,0) | C82: =+VLOOKUP(B82,ARTICULOS!$D$10:$I$699,6) | D82: Resite Antimanchas | E82: =+C82&F82 | F82: 1 | G82: Blanco | H82: 5.99 | I82: 1.6 | J82: 100% Poliester
A83: =ROW()-6 | B83: =+MATCH(D83,ARTICULOS!$F$10:$F$699,0) | C83: =+VLOOKUP(B83,ARTICULOS!$D$10:$I$699,6) | D83: Resite Antimanchas | E83: =+C83&F83 | F83: 7 | G83: Verde | H83: 5.99 | I83: 1.6 | J83: 100% Poliester
A84: =ROW()-6 | B84: =+MATCH(D84,ARTICULOS!$F$10:$F$699,0) | C84: =+VLOOKUP(B84,ARTICULOS!$D$10:$I$699,6) | D84: Saten Antimanchas | E84: =+C84&F84 | F84: 1 | G84: Blanco | H84: 10.89 | I84: 3.25 | J84: 100% Poliester
A85: =ROW()-6 | B85: =+MATCH(D85,ARTICULOS!$F$10:$F$699,0) | C85: =+VLOOKUP(B85,ARTICULOS!$D$10:$I$699,6) | D85: Gouble M | E85: =+C85&F85 | F85: 1 | G85: Color | H85: 8.45 | I85: 2.8 | J85: 62%CO 38%PES
A86: =ROW()-6 | B86: =+MATCH(D86,ARTICULOS!$F$10:$F$699,0) | C86: =+VLOOKUP(B86,ARTICULOS!$D$10:$I$699,6) | D86: Trivial | E86: =+C86&F86 | F86: 1 | G86: Granate | H86: 8.7 | I86: 2.8 | J86: 62%CO 38%PES
A87: =ROW()-6 | B87: =+MATCH(D87,ARTICULOS!$F$10:$F$699,0) | C87: =+VLOOKUP(B87,ARTICULOS!$D$10:$I$699,6) | D87: Saten I 50/50 | E87: =+C87&F87 | F87: 4P | G87: Beige | H87: 6.34 | I87: 3.2 | J87: 50% Alg./50%Pes.
A88: =ROW()-6 | B88: =+MATCH(D88,ARTICULOS!$F$10:$F$699,0) | C88: =+VLOOKUP(B88,ARTICULOS!$D$10:$I$699,6) | D88: Milano Pol.100 | E88: =+C88&F88 | F88: 11P | G88: Beige | H88: 5.63 | I88: 3.2 | J88: 100% Poliester
A89: =ROW()-6 | B89: =+MATCH(D89,ARTICULOS!$F$10:$F$699,0) | C89: =+VLOOKUP(B89,ARTICULOS!$D$10:$I$699,6) | D89: Saten I 65/35 | E89: =+C89&F89 | F89: 4 | G89: Beige | H89: 5.9 | I89: 3.2 | J89: 35% Alg./65%Pes.
A90: =ROW()-6 | B90: =+MATCH(D90,ARTICULOS!$F$10:$F$699,0) | C90: =+VLOOKUP(B90,ARTICULOS!$D$10:$I$699,6) | D90: Loneta Prisma | E90: =+C90&F90 | F90: 100 | G90: Negro | H90: 7.98 | I90: 2.8 | J90: 50% Alg./50%Pes.
A91: =ROW()-6 | B91: =+MATCH(D91,ARTICULOS!$F$10:$F$699,0) | C91: =+VLOOKUP(B91,ARTICULOS!$D$10:$I$699,6) | D91: LinoPoliester | E91: =+C91&F91 | F91: 7 | G91: Granate | H91: 14.27 | I91: 3.3
A92: =ROW()-6 | B92: =+MATCH(D92,ARTICULOS!$F$10:$F$699,0) | C92: =+VLOOKUP(B92,ARTICULOS!$D$10:$I$699,6) | D92: LinoPoliester | E92: =+C92&F92 | F92: 13 | G92: Gris Perla | H92: 13.41 | I92: 3.3
A93: =ROW()-6 | B93: =+MATCH(D93,ARTICULOS!$F$10:$F$699,0) | C93: =+VLOOKUP(B93,ARTICULOS!$D$10:$I$699,6) | D93: LinoPoliester | E93: =+C93&F93 | F93: 17 | G93: Tostado | H93: 14.27 | I93: 3.3
A94: =ROW()-6 | B94: =+MATCH(D94,ARTICULOS!$F$10:$F$699,0) | C94: =+VLOOKUP(B94,ARTICULOS!$D$10:$I$699,6) | D94: Saten Liso Nacional | E94: =+C94&F94 | F94: 65 | G94: Gris | H94: 9.16 | I94: 3.3 | J94: 50% Alg./50%Pes.
A95: =ROW()-6 | B95: =+MATCH(D95,ARTICULOS!$F$10:$F$699,0) | C95: =+VLOOKUP(B95,ARTICULOS!$D$10:$I$699,6) | D95: LinoPoliester | E95: =+C95&F95 | F95: 4 | G95: Gold | H95: 13.41 | I95: 3.3
A96: =ROW()-6 | B96: =+MATCH(D96,ARTICULOS!$F$10:$F$699,0) | C96: =+VLOOKUP(B96,ARTICULOS!$D$10:$I$699,6) | D96: Tagore Pes100 | E96: =+C96&F96 | F96: 74 | G96: Frambuesa | H96: 7.67 | I96: 3.2
A97: =ROW()-6 | B97: =+MATCH(D97,ARTICULOS!$F$10:$F$699,0) | C97: =+VLOOKUP(B97,ARTICULOS!$D$10:$I$699,6) | D97: LinoPoliester | E97: =+C97&F97 | F97: 14 | G97: Beige | H97: 13.41 | I97: 3.3
A98: =ROW()-6 | B98: =+MATCH(D98,ARTICULOS!$F$10:$F$699,0) | C98: =+VLOOKUP(B98,ARTICULOS!$D$10:$I$699,6) | D98: Bellini | E98: =+C98&F98 | F98: 13 | G98: Negro | H98: 13.6 | I98: 2.8 | J98: 100% Poliester
A99: =ROW()-6 | B99: =+MATCH(D99,ARTICULOS!$F$10:$F$699,0) | C99: =+VLOOKUP(B99,ARTICULOS!$D$10:$I$699,6) | D99: Ninfa | E99: =+C99&F99 | F99: 59 | G99: Mostaza | H99: 8.72 | I99: 2.8 | J99: 100% Poliester
A100: =ROW()-6 | B100: =+MATCH(D100,ARTICULOS!$F$10:$F$699,0) | C100: =+VLOOKUP(B100,ARTICULOS!$D$10:$I$699,6) | D100: Ninfa M | E100: =+C100&F100 | F100: 59 | G100: Mostaza | H100: 13.07 | I100: 2.8 | J100: 100% Poliester
A101: =ROW()-6 | B101: =+MATCH(D101,ARTICULOS!$F$10:$F$699,0) | C101: =+VLOOKUP(B101,ARTICULOS!$D$10:$I$699,6) | D101: Santorini | E101: =+C101&F101 | F101: 11 | G101: Marfil | H101: 12.8 | I101: 3.4 | J101: 100% Poliester
A102: =ROW()-6 | B102: =+MATCH(D102,ARTICULOS!$F$10:$F$699,0) | C102: =+VLOOKUP(B102,ARTICULOS!$D$10:$I$699,6) | D102: Santorini | E102: =+C102&F102 | F102: 0 | G102: Negro | H102: 12.8 | I102: 3.4 | J102: 100% Poliester
A103: =ROW()-6 | B103: =+MATCH(D103,ARTICULOS!$F$10:$F$699,0) | C103: =+VLOOKUP(B103,ARTICULOS!$D$10:$I$699,6) | D103: Saten Algodon | E103: =+C103&F103 | F103: 1 | G103: Blanco | H103: 8.12 | I103: 3.3 | J103: 100% Algodón
A104: =ROW()-6 | B104: =+MATCH(D104,ARTICULOS!$F$10:$F$699,0) | C104: =+VLOOKUP(B104,ARTICULOS!$D$10:$I$699,6) | D104: Saten Algodon | E104: =+C104&F104 | F104: 2 | G104: Crudo | H104: 10.03 | I104: 3.3 | J104: 100% Algodón
A105: =ROW()-6 | B105: =+MATCH(D105,ARTICULOS!$F$10:$F$699,0) | C105: =+VLOOKUP(B105,ARTICULOS!$D$10:$I$699,6) | D105: Lido | E105: =+C105&F105 | F105: 1 | G105: Crudo | H105: 13.3 | I105: 2.8
A106: =ROW()-6 | B106: =+MATCH(D106,ARTICULOS!$F$10:$F$699,0) | C106: =+VLOOKUP(B106,ARTICULOS!$D$10:$I$699,6) | D106: Triunfo | E106: =+C106&F106 | F106: 56 | G106: Avellana | H106: 12.73 | I106: 3.2 | J106: 50% Alg./50%Pes.
A107: =ROW()-6 | B107: =+MATCH(D107,ARTICULOS!$F$10:$F$699,0) | C107: =+VLOOKUP(B107,ARTICULOS!$D$10:$I$699,6) | D107: Nido | E107: =+C107&F107 | F107: 1 | G107: Negro | H107: 9 | I107: 1.5
A108: =ROW()-6 | B108: =+MATCH(D108,ARTICULOS!$F$10:$F$699,0) | C108: =+VLOOKUP(B108,ARTICULOS!$D$10:$I$699,6) | D108: Baroja | E108: =+C108&F108 | F108: 1 | G108: Crudo | H108: 8.55 | I108: 1.4
A109: =ROW()-6 | B109: =+MATCH(D109,ARTICULOS!$F$10:$F$699,0) | C109: =+VLOOKUP(B109,ARTICULOS!$D$10:$I$699,6) | E109: =+C109&F109
A110: =ROW()-6 | B110: =+MATCH(D110,ARTICULOS!$F$10:$F$699,0) | C110: =+VLOOKUP(B110,ARTICULOS!$D$10:$I$699,6) | E110: =+C110&F110
A111: =ROW()-6 | B111: =+MATCH(D111,ARTICULOS!$F$10:$F$699,0) | C111: =+VLOOKUP(B111,ARTICULOS!$D$10:$I$699,6) | E111: =+C111&F111
A112: =ROW()-6 | B112: =+MATCH(D112,ARTICULOS!$F$10:$F$699,0) | C112: =+VLOOKUP(B112,ARTICULOS!$D$10:$I$699,6) | E112: =+C112&F112
A113: =ROW()-6 | B113: =+MATCH(D113,ARTICULOS!$F$10:$F$699,0) | C113: =+VLOOKUP(B113,ARTICULOS!$D$10:$I$699,6) | E113: =+C113&F113
A114: =ROW()-6 | B114: =+MATCH(D114,ARTICULOS!$F$10:$F$699,0) | C114: =+VLOOKUP(B114,ARTICULOS!$D$10:$I$699,6) | E114: =+C114&F114
A115: =ROW()-6 | B115: =+MATCH(D115,ARTICULOS!$F$10:$F$699,0) | C115: =+VLOOKUP(B115,ARTICULOS!$D$10:$I$699,6) | E115: =+C115&F115
A116: =ROW()-6 | B116: =+MATCH(D116,ARTICULOS!$F$10:$F$699,0) | C116: =+VLOOKUP(B116,ARTICULOS!$D$10:$I$699,6) | E116: =+C116&F116
A117: =ROW()-6 | B117: =+MATCH(D117,ARTICULOS!$F$10:$F$699,0) | C117: =+VLOOKUP(B117,ARTICULOS!$D$10:$I$699,6) | E117: =+C117&F117
A118: =ROW()-6 | B118: =+MATCH(D118,ARTICULOS!$F$10:$F$699,0) | C118: =+VLOOKUP(B118,ARTICULOS!$D$10:$I$699,6) | E118: =+C118&F118
A119: =ROW()-6 | B119: =+MATCH(D119,ARTICULOS!$F$10:$F$699,0) | C119: =+VLOOKUP(B119,ARTICULOS!$D$10:$I$699,6) | E119: =+C119&F119
A120: =ROW()-6 | B120: =+MATCH(D120,ARTICULOS!$F$10:$F$699,0) | C120: =+VLOOKUP(B120,ARTICULOS!$D$10:$I$699,6) | E120: =+C120&F120
... A4394: =ROW()-6 | B4394: =+MATCH(D4394,ARTICULOS!$F$10:$F$699,0) | C4394: =+VLOOKUP(B4394,ARTICULOS!$D$10:$I$699,6) | E4394: =+C4394&F4394

Sheet EMPALME
A1: ANCHO DEL TEJIDO | B1: ANCHO DEL MANTEL | C1: REF. EMPALME | D1: LARGO EMPALME | E1: ANCHO EMPALME | F1: AL ANCHO SALEN
A2: 280 | B2: 300 | C2: =+A2&B2 | D2: 110 | E2: =+B2-A2+2 | F2: =INT(A2/E2)
A3: 280 | B3: 305 | C3: =+A3&B3 | D3: 160 | E3: =+B3-A3+2 | F3: =INT(A3/E3)
A4: 280 | B4: 310 | C4: =+A4&B4 | D4: 170 | E4: =+B4-A4+2 | F4: =INT(A4/E4)
A5: 280 | B5: 315 | C5: =+A5&B5 | D5: 190 | E5: =+B5-A5+2 | F5: =INT(A5/E5)
A6: 280 | B6: 320 | C6: =+A6&B6 | D6: 200 | E6: =+B6-A6+2 | F6: =INT(A6/E6)
A7: 280 | B7: 325 | C7: =+A7&B7 | D7: 230 | E7: =+B7-A7+2 | F7: =INT(A7/E7)
A8: 280 | B8: 330 | C8: =+A8&B8 | D8: 245 | E8: =+B8-A8+2 | F8: =INT(A8/E8)
A9: 280 | B9: 335 | C9: =+A9&B9 | D9: 260 | E9: =+B9-A9+2 | F9: =INT(A9/E9)
A10: 280 | B10: 340 | C10: =+A10&B10 | D10: 265 | E10: =+B10-A10+2 | F10: =INT(A10/E10)
A11: 280 | B11: 345 | C11: =+A11&B11 | D11: 290 | E11: =+B11-A11+2 | F11: =INT(A11/E11)
A12: 280 | B12: 350 | C12: =+A12&B12 | D12: 295 | E12: =+B12-A12+2 | F12: =INT(A12/E12)
A13: 280 | B13: 360 | C13: =+A13&B13 | D13: 300 | E13: =+B13-A13+2 | F13: =INT(A13/E13)
... A33: 330 | B33: 350 | C33: =+A33&B33 | D33: 275 | E33: =+B33-A33+2 | F33: =INT(A33/E33)

Sheet CONFECCION
B2: TARIFA DE CONFECCIÓN 2003
B4: METROS | C4: 0.5 | D4: =C4+0.5 | E4: =D4+0.5 | F4: =E4+0.5 | G4: =F4+0.5 | H4: =G4+0.5 | I4: =H4+0.5 | J4: =I4+0.5 | K4: =J4+0.5 | ... P4: =O4+0.5
B5: 0.5 | C5: =0.36*(1+3.5%) | D5: =0.45*(1+3.5%) | E5: =0.54*(1+3.5%) | F5: =0.63*(1+3.5%) | G5: =0.72*(1+3.5%) | H5: =0.81*(1+3.5%) | I5: =0.9*(1+3.5%) | J5: =1*(1+3.5%) | K5: =1.08*(1+3.5%) | L5: =1.17*(1+3.5%) | M5: =1.26*(1+3.5%) | N5: =1.35*(1+3.5%) | O5: =1.44*(1+3.5%) | P5: =1.53*(1+3.5%)
B6: =B5+0.5 | C6: =0.45*(1+3.5%) | D6: =0.54*(1+3.5%) | E6: =0.63*(1+3.5%) | F6: =0.72*(1+3.5%) | G6: =0.81*(1+3.5%) | H6: =0.9*(1+3.5%) | I6: =1*(1+3.5%) | J6: =1.08*(1+3.5%) | K6: =1.17*(1+3.5%) | L6: =1.26*(1+3.5%) | M6: =1.35*(1+3.5%) | N6: =1.44*(1+3.5%) | O6: =1.53*(1+3.5%) | P6: =1.62*(1+3.5%)
B7: =B6+0.5 | C7: =0.54*(1+3.5%) | D7: =0.63*(1+3.5%) | E7: =0.72*(1+3.5%) | F7: =0.81*(1+3.5%) | G7: =0.9*(1+3.5%) | H7: =1*(1+3.5%) | I7: =1.08*(1+3.5%) | J7: =1.17*(1+3.5%) | K7: =1.26*(1+3.5%) | L7: =1.35*(1+3.5%) | M7: =1.44*(1+3.5%) | N7: =1.53*(1+3.5%) | O7: =1.62*(1+3.5%) | P7: =1.71*(1+3.5%)
B8: =B7+0.5 | C8: =0.63*(1+3.5%) | D8: =0.72*(1+3.5%) | E8: =0.81*(1+3.5%) | F8: =0.9*(1+3.5%) | G8: =1*(1+3.5%) | H8: =1.08*(1+3.5%) | I8: =1.17*(1+3.5%) | J8: =1.26*(1+3.5%) | K8: =1.35*(1+3.5%) | L8: =1.44*(1+3.5%) | M8: =1.53*(1+3.5%) | N8: =1.62*(1+3.5%) | O8: =1.71*(1+3.5%) | P8: =1.8*(1+3.5%)
B9: =B8+0.5 | C9: =0.72*(1+3.5%) | D9: =0.81*(1+3.5%) | E9: =0.9*(1+3.5%) | F9: =1*(1+3.5%) | G9: =1.08*(1+3.5%) | H9: =1.17*(1+3.5%) | I9: =1.26*(1+3.5%) | J9: =1.35*(1+3.5%) | K9: =1.44*(1+3.5%) | L9: =1.53*(1+3.5%) | M9: =1.62*(1+3.5%) | N9: =1.71*(1+3.5%) | O9: =1.8*(1+3.5%) | P9: =1.89*(1+3.5%)
B10: =B9+0.5 | C10: =0.81*(1+3.5%) | D10: =0.9*(1+3.5%) | E10: =1*(1+3.5%) | F10: =1.08*(1+3.5%) | G10: =1.17*(1+3.5%) | H10: =1.26*(1+3.5%) | I10: =1.35*(1+3.5%) | J10: =1.44*(1+3.5%) | K10: =1.53*(1+3.5%) | L10: =1.62*(1+3.5%) | M10: =1.71*(1+3.5%) | N10: =1.8*(1+3.5%) | O10: =1.89*(1+3.5%) | P10: =1.98*(1+3.5%)
B11: =B10+0.5 | C11: =0.9*(1+3.5%) | D11: =1*(1+3.5%) | E11: =1.08*(1+3.5%) | F11: =1.17*(1+3.5%) | G11: =1.26*(1+3.5%) | H11: =1.35*(1+3.5%) | I11: =1.44*(1+3.5%) | J11: =1.53*(1+3.5%) | K11: =1.62*(1+3.5%) | L11: =1.71*(1+3.5%) | M11: =1.8*(1+3.5%) | N11: =1.89*(1+3.5%) | O11: =1.98*(1+3.5%) | P11: =2.07*(1+3.5%)
B12: =B11+0.5 | C12: =1*(1+3.5%) | D12: =1.08*(1+3.5%) | E12: =1.17*(1+3.5%) | F12: =1.26*(1+3.5%) | G12: =1.35*(1+3.5%) | H12: =1.44*(1+3.5%) | I12: =1.53*(1+3.5%) | J12: =1.62*(1+3.5%) | K12: =1.71*(1+3.5%) | L12: =1.8*(1+3.5%) | M12: =1.89*(1+3.5%) | N12: =1.98*(1+3.5%) | O12: =2.07*(1+3.5%) | P12: =2.16*(1+3.5%)
B15: Los precios de la confección con dobladillo a dos centímetros, son los anteriores multiplicados por dos
B17: Nº Fila | C17: 1 | D17: 50 | E17: 51 | F17: 100 | G17: 101 | H17: 150 | I17: 151 | J17: 200 | K17: 201 | L17: 250 | M17: 251 | N17: 300 | O17: 301 | P17: 350 | Q17: 351 | R17: 400 | S17: 401 | T17: 450 | U17: 451 | V17: 500 | W17: 501 | X17: 550 | Y17: 551 | Z17: 600 | AA17: 601 | AB17: 650 | AC17: 651 | AD17: 700
A18: 1 | B18: =ROW(A18) | C18: =0.36*(1+3.5%) | D18: =0.36*(1+3.5%) | E18: =0.45*(1+3.5%) | F18: =0.45*(1+3.5%) | G18: 0.54 | H18: =0.54*(1+3.5%) | I18: =0.63*(1+3.5%) | J18: =0.63*(1+3.5%) | K18: =0.72*(1+3.5%) | L18: =0.72*(1+3.5%) | M18: =0.81*(1+3.5%) | N18: =0.81*(1+3.5%) | O18: =0.9*(1+3.5%) | P18: =0.9*(1+3.5%) | Q18: =1*(1+3.5%) | R18: =1*(1+3.5%) | S18: =1.08*(1+3.5%) | T18: =1.08*(1+3.5%) | U18: =1.17*(1+3.5%) | V18: =1.17*(1+3.5%) | W18: =1.26*(1+3.5%) | X18: =1.26*(1+3.5%) | Y18: =1.35*(1+3.5%) | Z18: =1.35*(1+3.5%) | AA18: =1.44*(1+3.5%) | AB18: =1.44*(1+3.5%) | AC18: =1.53*(1+3.5%) | AD18: =1.53*(1+3.5%)
A19: 50 | B19: =ROW(A19) | C19: =0.36*(1+3.5%) | D19: =0.36*(1+3.5%) | E19: =0.45*(1+3.5%) | F19: =0.45*(1+3.5%) | G19: =0.54*(1+3.5%) | H19: =0.54*(1+3.5%) | I19: =0.63*(1+3.5%) | J19: =0.63*(1+3.5%) | K19: =0.72*(1+3.5%) | L19: =0.72*(1+3.5%) | M19: =0.81*(1+3.5%) | N19: =0.81*(1+3.5%) | O19: =0.9*(1+3.5%) | P19: =0.9*(1+3.5%) | Q19: =1*(1+3.5%) | R19: =1*(1+3.5%) | S19: =1.08*(1+3.5%) | T19: =1.08*(1+3.5%) | U19: =1.17*(1+3.5%) | V19: =1.17*(1+3.5%) | W19: =1.26*(1+3.5%) | X19: =1.26*(1+3.5%) | Y19: =1.35*(1+3.5%) | Z19: =1.35*(1+3.5%) | AA19: =1.44*(1+3.5%) | AB19: =1.44*(1+3.5%) | AC19: =1.53*(1+3.5%) | AD19: =1.53*(1+3.5%)
A20: =A19+1 | B20: =ROW(A20) | C20: =0.45*(1+3.5%) | D20: =0.45*(1+3.5%) | E20: =0.54*(1+3.5%) | F20: =0.54*(1+3.5%) | G20: =0.63*(1+3.5%) | H20: =0.63*(1+3.5%) | I20: =0.72*(1+3.5%) | J20: =0.72*(1+3.5%) | K20: =0.81*(1+3.5%) | L20: =0.81*(1+3.5%) | M20: =0.9*(1+3.5%) | N20: =0.9*(1+3.5%) | O20: =1*(1+3.5%) | P20: =1*(1+3.5%) | Q20: =1.08*(1+3.5%) | R20: =1.08*(1+3.5%) | S20: =1.17*(1+3.5%) | T20: =1.17*(1+3.5%) | U20: =1.26*(1+3.5%) | V20: =1.26*(1+3.5%) | W20: =1.35*(1+3.5%) | X20: =1.35*(1+3.5%) | Y20: =1.44*(1+3.5%) | Z20: =1.44*(1+3.5%) | AA20: =1.53*(1+3.5%) | AB20: =1.53*(1+3.5%) | AC20: =1.62*(1+3.5%) | AD20: =1.62*(1+3.5%)
A21: 100 | B21: =ROW(A21) | C21: =0.45*(1+3.5%) | D21: =0.45*(1+3.5%) | E21: =0.54*(1+3.5%) | F21: =0.54*(1+3.5%) | G21: =0.63*(1+3.5%) | H21: =0.63*(1+3.5%) | I21: =0.72*(1+3.5%) | J21: =0.72*(1+3.5%) | K21: =0.81*(1+3.5%) | L21: =0.81*(1+3.5%) | M21: =0.9*(1+3.5%) | N21: =0.9*(1+3.5%) | O21: =1*(1+3.5%) | P21: =1*(1+3.5%) | Q21: =1.08*(1+3.5%) | R21: =1.08*(1+3.5%) | S21: =1.17*(1+3.5%) | T21: =1.17*(1+3.5%) | U21: =1.26*(1+3.5%) | V21: =1.26*(1+3.5%) | W21: =1.35*(1+3.5%) | X21: =1.35*(1+3.5%) | Y21: =1.44*(1+3.5%) | Z21: =1.44*(1+3.5%) | AA21: =1.53*(1+3.5%) | AB21: =1.53*(1+3.5%) | AC21: =1.62*(1+3.5%) | AD21: =1.62*(1+3.5%)
A22: =A21+1 | B22: =ROW(A22) | C22: =0.54*(1+3.5%) | D22: =0.54*(1+3.5%) | E22: =0.63*(1+3.5%) | F22: =0.63*(1+3.5%) | G22: =0.72*(1+3.5%) | H22: =0.72*(1+3.5%) | I22: =0.81*(1+3.5%) | J22: =0.81*(1+3.5%) | K22: =0.9*(1+3.5%) | L22: =0.9*(1+3.5%) | M22: =1*(1+3.5%) | N22: =1*(1+3.5%) | O22: =1.08*(1+3.5%) | P22: =1.08*(1+3.5%) | Q22: =1.17*(1+3.5%) | R22: =1.17*(1+3.5%) | S22: =1.26*(1+3.5%) | T22: =1.26*(1+3.5%) | U22: =1.35*(1+3.5%) | V22: =1.35*(1+3.5%) | W22: =1.44*(1+3.5%) | X22: =1.44*(1+3.5%) | Y22: =1.53*(1+3.5%) | Z22: =1.53*(1+3.5%) | AA22: =1.62*(1+3.5%) | AB22: =1.62*(1+3.5%) | AC22: =1.71*(1+3.5%) | AD22: =1.71*(1+3.5%)
A23: 150 | B23: =ROW(A23) | C23: =0.54*(1+3.5%) | D23: =0.54*(1+3.5%) | E23: =0.63*(1+3.5%) | F23: =0.63*(1+3.5%) | G23: =0.72*(1+3.5%) | H23: =0.72*(1+3.5%) | I23: =0.81*(1+3.5%) | J23: =0.81*(1+3.5%) | K23: =0.9*(1+3.5%) | L23: =0.9*(1+3.5%) | M23: =1*(1+3.5%) | N23: =1*(1+3.5%) | O23: =1.08*(1+3.5%) | P23: =1.08*(1+3.5%) | Q23: =1.17*(1+3.5%) | R23: =1.17*(1+3.5%) | S23: =1.26*(1+3.5%) | T23: =1.26*(1+3.5%) | U23: =1.35*(1+3.5%) | V23: =1.35*(1+3.5%) | W23: =1.44*(1+3.5%) | X23: =1.44*(1+3.5%) | Y23: =1.53*(1+3.5%) | Z23: =1.53*(1+3.5%) | AA23: =1.62*(1+3.5%) | AB23: =1.62*(1+3.5%) | AC23: =1.71*(1+3.5%) | AD23: =1.71*(1+3.5%)
A24: 151 | B24: =ROW(A24) | C24: =0.63*(1+3.5%) | D24: =0.63*(1+3.5%) | E24: =0.72*(1+3.5%) | F24: =0.72*(1+3.5%) | G24: =0.81*(1+3.5%) | H24: =0.81*(1+3.5%) | I24: =0.9*(1+3.5%) | J24: =0.9*(1+3.5%) | K24: =1*(1+3.5%) | L24: =1*(1+3.5%) | M24: =1.08*(1+3.5%) | N24: =1.08*(1+3.5%) | O24: =1.17*(1+3.5%) | P24: =1.17*(1+3.5%) | Q24: =1.26*(1+3.5%) | R24: =1.26*(1+3.5%) | S24: =1.35*(1+3.5%) | T24: =1.35*(1+3.5%) | U24: =1.44*(1+3.5%) | V24: =1.44*(1+3.5%) | W24: =1.53*(1+3.5%) | X24: =1.53*(1+3.5%) | Y24: =1.62*(1+3.5%) | Z24: =1.62*(1+3.5%) | AA24: =1.71*(1+3.5%) | AB24: =1.71*(1+3.5%) | AC24: =1.8*(1+3.5%) | AD24: =1.8*(1+3.5%)
A25: 200 | B25: =ROW(A25) | C25: =0.63*(1+3.5%) | D25: =0.63*(1+3.5%) | E25: =0.72*(1+3.5%) | F25: =0.72*(1+3.5%) | G25: =0.81*(1+3.5%) | H25: =0.81*(1+3.5%) | I25: =0.9*(1+3.5%) | J25: =0.9*(1+3.5%) | K25: =1*(1+3.5%) | L25: =1*(1+3.5%) | M25: =1.08*(1+3.5%) | N25: =1.08*(1+3.5%) | O25: =1.17*(1+3.5%) | P25: =1.17*(1+3.5%) | Q25: =1.26*(1+3.5%) | R25: =1.26*(1+3.5%) | S25: =1.35*(1+3.5%) | T25: =1.35*(1+3.5%) | U25: =1.44*(1+3.5%) | V25: =1.44*(1+3.5%) | W25: =1.53*(1+3.5%) | X25: =1.53*(1+3.5%) | Y25: =1.62*(1+3.5%) | Z25: =1.62*(1+3.5%) | AA25: =1.71*(1+3.5%) | AB25: =1.71*(1+3.5%) | AC25: =1.8*(1+3.5%) | AD25: =1.8*(1+3.5%)
A26: =A25+1 | B26: =ROW(A26) | C26: =0.72*(1+3.5%) | D26: =0.72*(1+3.5%) | E26: =0.81*(1+3.5%) | F26: =0.81*(1+3.5%) | G26: =0.9*(1+3.5%) | H26: =0.9*(1+3.5%) | I26: =1*(1+3.5%) | J26: =1*(1+3.5%) | K26: =1.08*(1+3.5%) | L26: =1.08*(1+3.5%) | M26: =1.17*(1+3.5%) | N26: =1.17*(1+3.5%) | O26: =1.26*(1+3.5%) | P26: =1.26*(1+3.5%) | Q26: =1.35*(1+3.5%) | R26: =1.35*(1+3.5%) | S26: =1.44*(1+3.5%) | T26: =1.44*(1+3.5%) | U26: =1.53*(1+3.5%) | V26: =1.53*(1+3.5%) | W26: =1.62*(1+3.5%) | X26: =1.62*(1+3.5%) | Y26: =1.71*(1+3.5%) | Z26: =1.71*(1+3.5%) | AA26: =1.8*(1+3.5%) | AB26: =1.8*(1+3.5%) | AC26: =1.89*(1+3.5%) | AD26: =1.89*(1+3.5%)
A27: 250 | B27: =ROW(A27) | C27: =0.72*(1+3.5%) | D27: =0.72*(1+3.5%) | E27: =0.81*(1+3.5%) | F27: =0.81*(1+3.5%) | G27: =0.9*(1+3.5%) | H27: =0.9*(1+3.5%) | I27: =1*(1+3.5%) | J27: =1*(1+3.5%) | K27: =1.08*(1+3.5%) | L27: =1.08*(1+3.5%) | M27: =1.17*(1+3.5%) | N27: =1.17*(1+3.5%) | O27: =1.26*(1+3.5%) | P27: =1.26*(1+3.5%) | Q27: =1.35*(1+3.5%) | R27: =1.35*(1+3.5%) | S27: =1.44*(1+3.5%) | T27: =1.44*(1+3.5%) | U27: =1.53*(1+3.5%) | V27: =1.53*(1+3.5%) | W27: =1.62*(1+3.5%) | X27: =1.62*(1+3.5%) | Y27: =1.71*(1+3.5%) | Z27: =1.71*(1+3.5%) | AA27: =1.8*(1+3.5%) | AB27: =1.8*(1+3.5%) | AC27: =1.89*(1+3.5%) | AD27: =1.89*(1+3.5%)
A28: 251 | B28: =ROW(A28) | C28: =0.81*(1+3.5%) | D28: =0.81*(1+3.5%) | E28: =0.9*(1+3.5%) | F28: =0.9*(1+3.5%) | G28: =1*(1+3.5%) | H28: =1*(1+3.5%) | I28: =1.08*(1+3.5%) | J28: =1.08*(1+3.5%) | K28: =1.17*(1+3.5%) | L28: =1.17*(1+3.5%) | M28: =1.26*(1+3.5%) | N28: =1.26*(1+3.5%) | O28: =1.35*(1+3.5%) | P28: =1.35*(1+3.5%) | Q28: =1.44*(1+3.5%) | R28: =1.44*(1+3.5%) | S28: =1.53*(1+3.5%) | T28: =1.53*(1+3.5%) | U28: =1.62*(1+3.5%) | V28: =1.62*(1+3.5%) | W28: =1.71*(1+3.5%) | X28: =1.71*(1+3.5%) | Y28: =1.8*(1+3.5%) | Z28: =1.8*(1+3.5%) | AA28: =1.89*(1+3.5%) | AB28: =1.89*(1+3.5%) | AC28: =1.98*(1+3.5%) | AD28: =1.98*(1+3.5%)
A29: 300 | B29: =ROW(A29) | C29: =0.81*(1+3.5%) | D29: =0.81*(1+3.5%) | E29: =0.9*(1+3.5%) | F29: =0.9*(1+3.5%) | G29: =1*(1+3.5%) | H29: =1*(1+3.5%) | I29: =1.08*(1+3.5%) | J29: =1.08*(1+3.5%) | K29: =1.17*(1+3.5%) | L29: =1.17*(1+3.5%) | M29: =1.26*(1+3.5%) | N29: =1.26*(1+3.5%) | O29: =1.35*(1+3.5%) | P29: =1.35*(1+3.5%) | Q29: =1.44*(1+3.5%) | R29: =1.44*(1+3.5%) | S29: =1.53*(1+3.5%) | T29: =1.53*(1+3.5%) | U29: =1.62*(1+3.5%) | V29: =1.62*(1+3.5%) | W29: =1.71*(1+3.5%) | X29: =1.71*(1+3.5%) | Y29: =1.8*(1+3.5%) | Z29: =1.8*(1+3.5%) | AA29: =1.89*(1+3.5%) | AB29: =1.89*(1+3.5%) | AC29: =1.98*(1+3.5%) | AD29: =1.98*(1+3.5%)
A30: 301 | B30: =ROW(A30) | C30: =0.9*(1+3.5%) | D30: =0.9*(1+3.5%) | E30: =1*(1+3.5%) | F30: =1*(1+3.5%) | G30: =1.08*(1+3.5%) | H30: =1.08*(1+3.5%) | I30: =1.17*(1+3.5%) | J30: =1.17*(1+3.5%) | K30: =1.26*(1+3.5%) | L30: =1.26*(1+3.5%) | M30: =1.35*(1+3.5%) | N30: =1.35*(1+3.5%) | O30: =1.44*(1+3.5%) | P30: =1.44*(1+3.5%) | Q30: =1.53*(1+3.5%) | R30: =1.53*(1+3.5%) | S30: =1.62*(1+3.5%) | T30: =1.62*(1+3.5%) | U30: =1.71*(1+3.5%) | V30: =1.71*(1+3.5%) | W30: =1.8*(1+3.5%) | X30: =1.8*(1+3.5%) | Y30: =1.89*(1+3.5%) | Z30: =1.89*(1+3.5%) | AA30: =1.98*(1+3.5%) | AB30: =1.98*(1+3.5%) | AC30: =2.07*(1+3.5%) | AD30: =2.07*(1+3.5%)
A31: 350 | B31: =ROW(A31) | C31: =0.9*(1+3.5%) | D31: =0.9*(1+3.5%) | E31: =1*(1+3.5%) | F31: =1*(1+3.5%) | G31: =1.08*(1+3.5%) | H31: =1.08*(1+3.5%) | I31: =1.17*(1+3.5%) | J31: =1.17*(1+3.5%) | K31: =1.26*(1+3.5%) | L31: =1.26*(1+3.5%) | M31: =1.35*(1+3.5%) | N31: =1.35*(1+3.5%) | O31: =1.44*(1+3.5%) | P31: =1.44*(1+3.5%) | Q31: =1.53*(1+3.5%) | R31: =1.53*(1+3.5%) | S31: =1.62*(1+3.5%) | T31: =1.62*(1+3.5%) | U31: =1.71*(1+3.5%) | V31: =1.71*(1+3.5%) | W31: =1.8*(1+3.5%) | X31: =1.8*(1+3.5%) | Y31: =1.89*(1+3.5%) | Z31: =1.89*(1+3.5%) | AA31: =1.98*(1+3.5%) | AB31: =1.98*(1+3.5%) | AC31: =2.07*(1+3.5%) | AD31: =2.07*(1+3.5%)
A32: 351 | B32: =ROW(A32) | C32: =1*(1+3.5%) | D32: =1*(1+3.5%) | E32: =1.08*(1+3.5%) | F32: =1.08*(1+3.5%) | G32: =1.17*(1+3.5%) | H32: =1.17*(1+3.5%) | I32: =1.26*(1+3.5%) | J32: =1.26*(1+3.5%) | K32: =1.35*(1+3.5%) | L32: =1.35*(1+3.5%) | M32: =1.44*(1+3.5%) | N32: =1.44*(1+3.5%) | O32: =1.53*(1+3.5%) | P32: =1.53*(1+3.5%) | Q32: =1.62*(1+3.5%) | R32: =1.62*(1+3.5%) | S32: =1.71*(1+3.5%) | T32: =1.71*(1+3.5%) | U32: =1.8*(1+3.5%) | V32: =1.8*(1+3.5%) | W32: =1.89*(1+3.5%) | X32: =1.89*(1+3.5%) | Y32: =1.98*(1+3.5%) | Z32: =1.98*(1+3.5%) | AA32: =2.07*(1+3.5%) | AB32: =2.07*(1+3.5%) | AC32: =2.16*(1+3.5%) | AD32: =2.16*(1+3.5%)
A33: 400 | B33: =ROW(A33) | C33: =1*(1+3.5%) | D33: =1*(1+3.5%) | E33: =1.08*(1+3.5%) | F33: =1.08*(1+3.5%) | G33: =1.17*(1+3.5%) | H33: =1.17*(1+3.5%) | I33: =1.26*(1+3.5%) | J33: =1.26*(1+3.5%) | K33: =1.35*(1+3.5%) | L33: =1.35*(1+3.5%) | M33: =1.44*(1+3.5%) | N33: =1.44*(1+3.5%) | O33: =1.53*(1+3.5%) | P33: =1.53*(1+3.5%) | Q33: =1.62*(1+3.5%) | R33: =1.62*(1+3.5%) | S33: =1.71*(1+3.5%) | T33: =1.71*(1+3.5%) | U33: =1.8*(1+3.5%) | V33: =1.8*(1+3.5%) | W33: =1.89*(1+3.5%) | X33: =1.89*(1+3.5%) | Y33: =1.98*(1+3.5%) | Z33: =1.98*(1+3.5%) | AA33: =2.07*(1+3.5%) | AB33: =2.07*(1+3.5%) | AC33: =2.16*(1+3.5%) | AD33: =2.16*(1+3.5%)
A35: FESTÓN | B35: 0.75 | C35: €/Mt.
